{"eventId": 1433, "source": "sportsoftware-pdf", "sourceUrl": "https://anne-cdn.oefol.at/public/legacy/event_1433_Ergebnis.pdf", "fileName": "event_1433_Ergebnis.pdf", "listType": "race", "docDate": "2015-04-11", "categories": [{"name": "Damen 19- NOe", "declaredStarters": 10, "results": [{"name": "Krischan Jutta", "club": "HSV OL Wiener Neustadt", "timeText": "33:35", "timeS": 2015, "status": "ok", "rank": 1}, {"name": "Linhart Gisa", "club": "HSV OL Wiener Neustadt", "timeText": "38:53", "rank": 2, "timeS": 2333, "status": "ok"}, {"name": "Peroutka Sophie", "club": "HSV OL Wiener Neustadt", "timeText": "39:23", "rank": 3, "timeS": 2363, "status": "ok"}, {"name": "Ponweiser Monika", "club": "HSV OL Wiener Neustadt", "timeText": "41:23", "rank": 4, "timeS": 2483, "status": "ok"}, {"name": "Aschacher Verena", "club": "HSV OL Wiener Neustadt", "timeText": "41:24", "rank": 5, "timeS": 2484, "status": "ok"}, {"name": "Mayer Julia", "club": "HSV Großmittel", "timeText": "43:12", "rank": 6, "timeS": 2592, "status": "ok"}, {"name": "Traint Christina", "club": "HSV OL Wiener Neustadt", "timeText": "1:00:00", "rank": 7, "timeS": 3600, "status": "ok"}, {"name": "Hofer Susanne", "club": "HSV Großmittel", "timeText": "1:00:41", "rank": 8, "timeS": 3641, "status": "ok"}, {"name": "Pauser Ida", "club": "HSV OL Wiener Neustadt", "timeText": "N Ang", "status": "dns"}, {"name": "Mangold Anita", "club": "HSV OL Wiener Neustadt", "timeText": "N Ang", "status": "dns"}], "courseLengthM": 3000, "courseClimbM": 160, "courseControls": 14}, {"name": "Herren 19- NOe", "declaredStarters": 11, "results": [{"name": "Braun Emanuel jun.", "club": "HSV OL Wiener Neustadt", "timeText": "35:43", "timeS": 2143, "status": "ok", "rank": 1}, {"name": "Plohn Markus", "club": "HSV OL Wiener Neustadt", "timeText": "37:10", "rank": 2, "timeS": 2230, "status": "ok"}, {"name": "Seeböck Stephan", "club": "HSV OL Wiener Neustadt", "timeText": "38:37", "rank": 3, "timeS": 2317, "status": "ok"}, {"name": "Auer Michael", "club": "HSV OL Wiener Neustadt", "timeText": "42:06", "rank": 4, "timeS": 2526, "status": "ok"}, {"name": "Arthofer Florian", "club": "HSV OL Wiener Neustadt", "timeText": "48:58", "rank": 5, "timeS": 2938, "status": "ok"}, {"name": "Peroutka Thomas", "club": "HSV OL Wiener Neustadt", "timeText": "55:11", "rank": 6, "timeS": 3311, "status": "ok"}, {"name": "Knapp Christian", "club": "Orienteering Klosterneuburg", "timeText": "1:17:50", "rank": 7, "timeS": 4670, "status": "ok"}, {"name": "Kaminger William", "club": "Orienteering Klosterneuburg", "timeText": "1:24:37", "rank": 8, "timeS": 5077, "status": "ok"}, {"name": "Palme Sebastian", "club": "Orienteering Klosterneuburg", "timeText": "N Ang", "status": "dns"}, {"name": "Fesselhofer Roland", "club": "HSV OL Wiener Neustadt", "timeText": "N Ang", "status": "dns"}, {"name": "Tanzer Michael", "club": "HSV Langenlebarn", "timeText": "N Ang", "status": "dns"}], "courseLengthM": 4600, "courseClimbM": 200, "courseControls": 24}, {"name": "Herren -12 NOe", "declaredStarters": 8, "results": [{"name": "Fedor Tibor", "club": "Sokol Pezinok", "timeText": "17:37", "rank": 1, "timeS": 1057, "status": "ok"}, {"name": "Ziegerhofer Maximilian", "club": "HSV OL Wiener Neustadt", "timeText": "17:54", "timeS": 1074, "status": "ok", "rank": 2}, {"name": "Tobler Simon", "club": "HSV OL Wiener Neustadt", "timeText": "18:36", "rank": 3, "timeS": 1116, "status": "ok"}, {"name": "Hofer Alexander", "club": "HSV OL Wiener Neustadt", "timeText": "25:21", "rank": 4, "timeS": 1521, "status": "ok"}, {"name": "Seidl Imanuel", "club": "HSV OL Wiener Neustadt", "timeText": "25:39", "rank": 5, "timeS": 1539, "status": "ok"}, {"name": "Rollinson Lucas", "club": "Orienteering Klosterneuburg", "timeText": "37:19", "rank": 6, "timeS": 2239, "status": "ok"}, {"name": "Heindl Clemens", "club": "Orienteering Klosterneuburg", "timeText": "50:22", "rank": 7, "timeS": 3022, "status": "ok"}, {"name": "Kirchmeir Yolanda", "club": "HSV OL Wiener Neustadt", "timeText": "Fehlst", "status": "mp"}], "courseLengthM": 1400, "courseClimbM": 70, "courseControls": 5}, {"name": "Herren -14 NOe", "declaredStarters": 7, "results": [{"name": "Christ Felix", "club": "HSV OL Wiener Neustadt", "timeText": "15:59", "timeS": 959, "status": "ok", "rank": 1}, {"name": "Pauser Leo", "club": "HSV OL Wiener Neustadt", "timeText": "17:48", "rank": 2, "timeS": 1068, "status": "ok"}, {"name": "Auer Merlin", "club": "HSV OL Wiener Neustadt", "timeText": "22:53", "rank": 3, "timeS": 1373, "status": "ok"}, {"name": "Rollinson Tim", "club": "Orienteering Klosterneuburg", "timeText": "26:34", "rank": 4, "timeS": 1594, "status": "ok"}, {"name": "Berger Peter", "club": "Orienteering Klosterneuburg", "timeText": "27:14", "rank": 5, "timeS": 1634, "status": "ok"}, {"name": "Müllner Joachim", "club": "HSV Langenlebarn", "timeText": "27:38", "rank": 6, "timeS": 1658, "status": "ok"}, {"name": "Jäger Ferdinand", "club": "Go Harzberg", "timeText": "N Ang", "status": "dns"}], "courseLengthM": 1600, "courseClimbM": 90, "courseControls": 9}, {"name": "Herren 15-18 NOe", "declaredStarters": 9, "results": [{"name": "Brantner Nikolas", "club": "HSV OL Wiener Neustadt", "timeText": "26:35", "timeS": 1595, "status": "ok", "rank": 1}, {"name": "Christ Oliver", "club": "HSV OL Wiener Neustadt", "timeText": "29:15", "rank": 2, "timeS": 1755, "status": "ok"}, {"name": "Micko Tobias", "club": "Go Harzberg", "timeText": "33:27", "rank": 3, "timeS": 2007, "status": "ok"}, {"name": "Palme Benjamin", "club": "Orienteering Klosterneuburg", "timeText": "39:37", "rank": 4, "timeS": 2377, "status": "ok"}, {"name": "Schuh Roman", "club": "Orienteering Klosterneuburg", "timeText": "42:26", "rank": 5, "timeS": 2546, "status": "ok"}, {"name": "Kirchmeir Constantin", "club": "HSV OL Wiener Neustadt", "timeText": "48:44", "rank": 6, "timeS": 2924, "status": "ok"}, {"name": "Fenk William", "club": "Go Harzberg", "timeText": "59:30", "rank": 7, "timeS": 3570, "status": "ok"}, {"name": "Deubel Joergen", "club": "Naturfreunde Wien", "timeText": "39:42", "timeS": 2382, "status": "ok", "outOfCompetition": true}, {"name": "Witzmann Florian", "club": "Go Harzberg", "timeText": "N Ang", "status": "dns"}], "courseLengthM": 3200, "courseClimbM": 160, "courseControls": 17}, {"name": "Herren 35- NOe", "declaredStarters": 11, "results": [{"name": "Kaltenbacher Pierre", "club": "HSV OL Wiener Neustadt", "timeText": "27:10", "timeS": 1630, "status": "ok", "rank": 1}, {"name": "Egger Jürgen", "club": "Leibnitzer AC", "timeText": "31:31", "rank": 2, "timeS": 1891, "status": "ok"}, {"name": "Hartberger Thomas", "club": "HSV OL Wiener Neustadt", "timeText": "36:01", "rank": 3, "timeS": 2161, "status": "ok"}, {"name": "Leidl Thomas", "club": "HSV OL Wiener Neustadt", "timeText": "37:23", "rank": 4, "timeS": 2243, "status": "ok"}, {"name": "Bednarik Martin", "club": "TJ Cingov Spisska Nova Ves", "timeText": "39:00", "rank": 5, "timeS": 2340, "status": "ok"}, {"name": "Sengstschmid Georg", "club": "HSV OL Wiener Neustadt", "timeText": "39:18", "rank": 6, "timeS": 2358, "status": "ok"}, {"name": "Pointner Werner", "club": "Naturfreunde Steiermark", "timeText": "39:28", "rank": 7, "timeS": 2368, "status": "ok"}, {"name": "Kellner Gottfried", "club": "HSV OL Wiener Neustadt", "timeText": "41:08", "rank": 8, "timeS": 2468, "status": "ok"}, {"name": "Fruhwirth Martin", "club": "HSV Langenlebarn", "timeText": "46:41", "rank": 9, "timeS": 2801, "status": "ok"}, {"name": "Hinterreither Markus", "club": "HSV OL Wiener Neustadt", "timeText": "53:14", "rank": 10, "timeS": 3194, "status": "ok"}, {"name": "Härtel Christian", "club": "Go Harzberg", "timeText": "N Ang", "status": "dns"}], "courseLengthM": 3400, "courseClimbM": 190, "courseControls": 18}, {"name": "Herren 45- NOe", "declaredStarters": 23, "results": [{"name": "Stockmayer Michael", "club": "HSV OL Wiener Neustadt", "timeText": "22:05", "timeS": 1325, "status": "ok", "rank": 1}, {"name": "Stockmayer Manfred", "club": "HSV OL Wiener Neustadt", "timeText": "25:40", "rank": 2, "timeS": 1540, "status": "ok"}, {"name": "Braun Emanuel", "club": "HSV OL Wiener Neustadt", "timeText": "27:34", "rank": 3, "timeS": 1654, "status": "ok"}, {"name": "Köck Erwin", "club": "HSV OL Wiener Neustadt", "timeText": "29:22", "rank": 4, "timeS": 1762, "status": "ok"}, {"name": "Kramer Klaus", "club": "Go Harzberg", "timeText": "30:09", "rank": 5, "timeS": 1809, "status": "ok"}, {"name": "Adenstedt Erik", "club": "Orienteering Klosterneuburg", "timeText": "33:54", "rank": 6, "timeS": 2034, "status": "ok"}, {"name": "Billroth Georg", "club": "Orienteering Klosterneuburg", "timeText": "34:24", "rank": 7, "timeS": 2064, "status": "ok"}, {"name": "Reisenberger Roland", "club": "Orienteering Klosterneuburg", "timeText": "34:54", "rank": 8, "timeS": 2094, "status": "ok"}, {"name": "Pauser Rainer", "club": "HSV OL Wiener Neustadt", "timeText": "35:30", "rank": 9, "timeS": 2130, "status": "ok"}, {"name": "Scheikl Gottfried", "club": "OC Fürstenfeld", "timeText": "36:21", "rank": 10, "timeS": 2181, "status": "ok"}, {"name": "Lipphart-Kirchmeir Harald", "club": "HSV OL Wiener Neustadt", "timeText": "37:30", "rank": 11, "timeS": 2250, "status": "ok"}, {"name": "Schenk Johannes", "club": "NF Linz", "timeText": "37:52", "rank": 12, "timeS": 2272, "status": "ok"}, {"name": "Praeceptor Rainer", "club": "Orienteering Klosterneuburg", "timeText": "38:07", "rank": 13, "timeS": 2287, "status": "ok"}, {"name": "Olearczick Erlefried", "club": "HSV Langenlebarn", "timeText": "38:22", "rank": 14, "timeS": 2302, "status": "ok"}, {"name": "Brenner Heimo", "club": "Orienteering Klosterneuburg", "timeText": "39:05", "rank": 15, "timeS": 2345, "status": "ok"}, {"name": "Jeschko Manfred", "club": "HSV Langenlebarn", "timeText": "39:50", "rank": 16, "timeS": 2390, "status": "ok"}, {"name": "Lundberg Urban", "club": "Orienteering Klosterneuburg", "timeText": "40:35", "rank": 17, "timeS": 2435, "status": "ok"}, {"name": "Adenstedt Nikolaus", "club": "Orienteering Klosterneuburg", "timeText": "41:36", "rank": 18, "timeS": 2496, "status": "ok"}, {"name": "Rotheneder Hannes", "club": "HSV Großmittel", "timeText": "45:17", "rank": 19, "timeS": 2717, "status": "ok"}, {"name": "Meissner Karl", "club": "HSV OL Wiener Neustadt", "timeText": "49:17", "rank": 20, "timeS": 2957, "status": "ok"}, {"name": "Blauensteiner Harald", "club": "Vereinslos (no club)", "timeText": "51:13", "rank": 21, "timeS": 3073, "status": "ok"}, {"name": "Sterba Markus", "club": "Orienteering Klosterneuburg", "timeText": "51:21", "rank": 22, "timeS": 3081, "status": "ok"}, {"name": "Novak Roland", "club": "HSV Großmittel", "timeText": "N Ang", "status": "dns"}], "courseLengthM": 3200, "courseClimbM": 160, "courseControls": 17}, {"name": "Herren 55- NOe", "declaredStarters": 8, "results": [{"name": "Hermann Claus", "club": "HSV OL Wiener Neustadt", "timeText": "23:25", "timeS": 1405, "status": "ok", "rank": 1}, {"name": "Schweifer Erwin", "club": "HSV OL Wiener Neustadt", "timeText": "23:37", "rank": 2, "timeS": 1417, "status": "ok"}, {"name": "Fedor Jozef", "club": "Sokol Pezinok", "timeText": "24:00", "rank": 3, "timeS": 1440, "status": "ok"}, {"name": "Drage Stefan", "club": "HSV OL Wiener Neustadt", "timeText": "24:59", "rank": 4, "timeS": 1499, "status": "ok"}, {"name": "Pidner Valentin", "club": "HSV OL Wiener Neustadt", "timeText": "29:36", "rank": 5, "timeS": 1776, "status": "ok"}, {"name": "Ponweiser Franz", "club": "HSV OL Wiener Neustadt", "timeText": "33:06", "rank": 6, "timeS": 1986, "status": "ok"}, {"name": "Mayer Ewald", "club": "HSV OL Wiener Neustadt", "timeText": "35:43", "rank": 7, "timeS": 2143, "status": "ok"}, {"name": "Molin Andreas", "club": "Orienteering Klosterneuburg", "timeText": "43:33", "rank": 8, "timeS": 2613, "status": "ok"}], "courseLengthM": 2400, "courseClimbM": 145, "courseControls": 12}, {"name": "Herren 65- NOe", "declaredStarters": 5, "results": [{"name": "Gurka Jiri", "club": "HSV OL Wiener Neustadt", "timeText": "20:29", "timeS": 1229, "status": "ok", "rank": 1}, {"name": "Lukaseder Hubert", "club": "HSV Langenlebarn", "timeText": "21:34", "rank": 2, "timeS": 1294, "status": "ok"}, {"name": "Holzinger Klaus", "club": "HSV Großmittel", "timeText": "26:58", "rank": 3, "timeS": 1618, "status": "ok"}, {"name": "Tobler Gottfried", "club": "HSV OL Wiener Neustadt", "timeText": "34:10", "rank": 4, "timeS": 2050, "status": "ok"}, {"name": "Fruhwirth Friedrich", "club": "HSV Langenlebarn", "timeText": "1:04:07", "rank": 5, "timeS": 3847, "status": "ok"}], "courseLengthM": 2000, "courseClimbM": 110, "courseControls": 12}, {"name": "Damen 35- NOe", "declaredStarters": 5, "results": [{"name": "Federova Katarina", "club": "Sokol Pezinok", "timeText": "27:09", "rank": 1, "timeS": 1629, "status": "ok"}, {"name": "Fuchs Bati", "club": "HSV OL Wiener Neustadt", "timeText": "35:07", "timeS": 2107, "status": "ok", "rank": 2}, {"name": "Tobler- Egger Gabriele", "club": "HSV OL Wiener Neustadt", "timeText": "38:27", "rank": 3, "timeS": 2307, "status": "ok"}, {"name": "Ponweiser Eva", "club": "HSV OL Wiener Neustadt", "timeText": "40:51", "rank": 4, "timeS": 2451, "status": "ok"}, {"name": "Tezarek Helga", "club": "Orienteering Klosterneuburg", "timeText": "Fehlst", "status": "mp"}], "courseLengthM": 2700, "courseClimbM": 150, "courseControls": 13}, {"name": "Damen 45- NOe", "declaredStarters": 7, "results": [{"name": "Berger Hedi", "club": "Orienteering Klosterneuburg", "timeText": "24:18", "timeS": 1458, "status": "ok", "rank": 1}, {"name": "Adenstedt Ingrid", "club": "Orienteering Klosterneuburg", "timeText": "29:10", "rank": 2, "timeS": 1750, "status": "ok"}, {"name": "Aschacher Angelika", "club": "HSV OL Wiener Neustadt", "timeText": "34:48", "rank": 3, "timeS": 2088, "status": "ok"}, {"name": "Kirchmeir Elisabeth", "club": "HSV OL Wiener Neustadt", "timeText": "37:14", "rank": 4, "timeS": 2234, "status": "ok"}, {"name": "Kaminger Ingrid", "club": "Orienteering Klosterneuburg", "timeText": "39:26", "rank": 5, "timeS": 2366, "status": "ok"}, {"name": "Ziegerhofer Petra", "club": "HSV OL Wiener Neustadt", "timeText": "41:14", "rank": 6, "timeS": 2474, "status": "ok"}, {"name": "Schreiber Hannelore", "club": "HSV Langenlebarn", "timeText": "45:52", "rank": 7, "timeS": 2752, "status": "ok"}], "courseLengthM": 2400, "courseClimbM": 145, "courseControls": 12}, {"name": "Damen 55- NOe", "declaredStarters": 6, "results": [{"name": "Knapp Elisabeth", "club": "Orienteering Klosterneuburg", "timeText": "21:35", "timeS": 1295, "status": "ok", "rank": 1}, {"name": "Fesselhofer Traude", "club": "HSV OL Wiener Neustadt", "timeText": "27:32", "rank": 2, "timeS": 1652, "status": "ok"}, {"name": "Fuchs Elisabeth", "club": "HSV OL Wiener Neustadt", "timeText": "28:29", "rank": 3, "timeS": 1709, "status": "ok"}, {"name": "Linhart Reingild", "club": "HSV OL Wiener Neustadt", "timeText": "28:31", "rank": 4, "timeS": 1711, "status": "ok"}, {"name": "Ponweiser Christine", "club": "HSV OL Wiener Neustadt", "timeText": "33:54", "rank": 5, "timeS": 2034, "status": "ok"}, {"name": "Tobler Barbara", "club": "HSV OL Wiener Neustadt", "timeText": "40:24", "rank": 6, "timeS": 2424, "status": "ok"}], "courseLengthM": 2000, "courseClimbM": 110, "courseControls": 12}, {"name": "Damen 15- Wien", "declaredStarters": 18, "results": [{"name": "Simkovics Anna", "club": "OLC Wienerwald", "timeText": "24:01", "timeS": 1441, "status": "ok", "rank": 1}, {"name": "Gassner Anika", "club": "Naturfreunde Wien", "timeText": "27:52", "rank": 2, "timeS": 1672, "status": "ok"}, {"name": "Trummer Johanna", "club": "OLC Graz", "timeText": "30:17", "rank": 3, "timeS": 1817, "status": "ok"}, {"name": "Tiefenböck Tina", "club": "Naturfreunde Wien", "timeText": "31:38", "rank": 4, "timeS": 1898, "status": "ok"}, {"name": "Kastner Ylvi", "club": "Naturfreunde Wien", "timeText": "31:39", "rank": 5, "timeS": 1899, "status": "ok"}, {"name": "Scheikl Agnes", "club": "OC Fürstenfeld", "timeText": "32:49", "rank": 6, "timeS": 1969, "status": "ok"}, {"name": "Skern Marina", "club": "Naturfreunde Wien", "timeText": "32:52", "rank": 7, "timeS": 1972, "status": "ok"}, {"name": "Bonek Claudia", "club": "Naturfreunde Wien", "timeText": "33:04", "rank": 8, "timeS": 1984, "status": "ok"}, {"name": "Waldmann Brigitte", "club": "OLT Transdanubien", "timeText": "37:03", "rank": 9, "timeS": 2223, "status": "ok"}, {"name": "Hnilica Lea", "club": "OLT Transdanubien", "timeText": "42:12", "rank": 10, "timeS": 2532, "status": "ok"}, {"name": "Hlosta Denise", "club": "Naturfreunde Wien", "timeText": "43:06", "rank": 11, "timeS": 2586, "status": "ok"}, {"name": "Engl Magdalena", "club": "OLC Wienerwald", "timeText": "44:05", "rank": 12, "timeS": 2645, "status": "ok"}, {"name": "Broinger Christina", "club": "OLC Wienerwald", "timeText": "47:52", "rank": 13, "timeS": 2872, "status": "ok"}, {"name": "Lyatoshinskaya Polina", "club": "OLC Wienerwald", "timeText": "48:58", "rank": 14, "timeS": 2938, "status": "ok"}, {"name": "Fabian Katharina", "club": "WAT", "timeText": "59:50", "rank": 15, "timeS": 3590, "status": "ok"}, {"name": "Wondraschek Sigrid", "club": "OLT Transdanubien", "timeText": "1:04:01", "rank": 16, "timeS": 3841, "status": "ok"}, {"name": "Kovacs Margit", "club": "OLT Transdanubien", "timeText": "1:16:06", "rank": 17, "timeS": 4566, "status": "ok"}, {"name": "Emde Sabine", "club": "OLC Wienerwald", "timeText": "1:17:33", "rank": 18, "timeS": 4653, "status": "ok"}], "courseLengthM": 3000, "courseClimbM": 160, "courseControls": 14}, {"name": "Herren 15- Wien", "declaredStarters": 47, "results": [{"name": "Simkovics Erik", "club": "OLC Wienerwald", "timeText": "31:18", "timeS": 1878, "status": "ok", "rank": 1}, {"name": "Glaner Franz", "club": "WAT", "timeText": "33:10", "rank": 2, "timeS": 1990, "status": "ok"}, {"name": "Siegert Wolfgang", "club": "WAT", "timeText": "33:11", "rank": 3, "timeS": 1991, "status": "ok"}, {"name": "Sulz Henrik", "club": "OLC Wienerwald", "timeText": "33:43", "rank": 4, "timeS": 2023, "status": "ok"}, {"name": "Waldmann Andreas", "club": "OLT Transdanubien", "timeText": "35:29", "rank": 5, "timeS": 2129, "status": "ok"}, {"name": "Kurz Florian", "club": "Naturfreunde Wien", "timeText": "35:54", "rank": 6, "timeS": 2154, "status": "ok"}, {"name": "Jandl Dominik", "club": "Naturfreunde Wien", "timeText": "38:09", "rank": 7, "timeS": 2289, "status": "ok"}, {"name": "Wolfram Clemens", "club": "Naturfreunde Wien", "timeText": "38:42", "rank": 8, "timeS": 2322, "status": "ok"}, {"name": "Radon Thomas", "club": "Naturfreunde Wien", "timeText": "40:30", "rank": 9, "timeS": 2430, "status": "ok"}, {"name": "Wibmer Andreas", "club": "OLT Transdanubien", "timeText": "41:13", "rank": 10, "timeS": 2473, "status": "ok"}, {"name": "Zete Vasile", "club": "Naturfreunde Wien", "timeText": "41:38", "rank": 11, "timeS": 2498, "status": "ok"}, {"name": "Bonek Peter", "club": "Naturfreunde Wien", "timeText": "43:20", "rank": 12, "timeS": 2600, "status": "ok"}, {"name": "Pölzl Andreas", "club": "Leibnitzer AC", "timeText": "43:24", "rank": 13, "timeS": 2604, "status": "ok"}, {"name": "Haider Philipp", "club": "WAT", "timeText": "43:26", "rank": 14, "timeS": 2606, "status": "ok"}, {"name": "Waldhäusl Wolfgang", "club": "OLC Wienerwald", "timeText": "43:31", "rank": 15, "timeS": 2611, "status": "ok"}, {"name": "Pietsch Werner", "club": "Naturfreunde Wien", "timeText": "43:36", "rank": 16, "timeS": 2616, "status": "ok"}, {"name": "Fabian Thomas", "club": "WAT", "timeText": "43:39", "rank": 17, "timeS": 2619, "status": "ok"}, {"name": "Bichl Daniel", "club": "WAT", "timeText": "43:53", "rank": 18, "timeS": 2633, "status": "ok"}, {"name": "Veitsberger Martin", "club": "OLT Transdanubien", "timeText": "44:51", "rank": 19, "timeS": 2691, "status": "ok"}, {"name": "Bonek Erik", "club": "Naturfreunde Wien", "timeText": "45:05", "rank": 20, "timeS": 2705, "status": "ok"}, {"name": "Danner Martin", "club": "OLC Wienerwald", "timeText": "48:25", "rank": 21, "timeS": 2905, "status": "ok"}, {"name": "Srb Alexander", "club": "WAT", "timeText": "51:11", "rank": 22, "timeS": 3071, "status": "ok"}, {"name": "Puchegger Stephan", "club": "WAT", "timeText": "51:36", "rank": 23, "timeS": 3096, "status": "ok"}, {"name": "Marksteiner Martin", "club": "WAT", "timeText": "55:03", "rank": 24, "timeS": 3303, "status": "ok"}, {"name": "Brettner-Messler Robert", "club": "Naturfreunde Wien", "timeText": "56:45", "rank": 25, "timeS": 3405, "status": "ok"}, {"name": "Kroupa Günther", "club": "Naturfreunde Wien", "timeText": "57:56", "rank": 26, "timeS": 3476, "status": "ok"}, {"name": "Satrapa Vito", "club": "OLC Wienerwald", "timeText": "1:01:41", "rank": 27, "timeS": 3701, "status": "ok"}, {"name": "Hack Thomas", "club": "WAT", "timeText": "1:02:13", "rank": 28, "timeS": 3733, "status": "ok"}, {"name": "Hampl Burkhard", "club": "WATV", "timeText": "1:04:13", "rank": 29, "timeS": 3853, "status": "ok"}, {"name": "Kainzbauer Peter", "club": "WAT", "timeText": "1:07:06", "rank": 30, "timeS": 4026, "status": "ok"}, {"name": "Mörth Markus", "club": "OLT Transdanubien", "timeText": "1:10:00", "rank": 31, "timeS": 4200, "status": "ok"}, {"name": "Manikas Niko", "club": "WAT", "timeText": "1:10:10", "rank": 32, "timeS": 4210, "status": "ok"}, {"name": "Huemer jun. Christoph", "club": "WAT", "timeText": "1:10:56", "rank": 33, "timeS": 4256, "status": "ok"}, {"name": "Pieler Michael", "club": "OLG Ströck Wien", "timeText": "1:11:39", "rank": 34, "timeS": 4299, "status": "ok"}, {"name": "Wolf Christian", "club": "WAT", "timeText": "1:13:49", "rank": 35, "timeS": 4429, "status": "ok"}, {"name": "Haring Alexander", "club": "WAT", "timeText": "1:14:24", "rank": 36, "timeS": 4464, "status": "ok"}, {"name": "Huemer Valentin", "club": "WAT", "timeText": "1:16:05", "rank": 37, "timeS": 4565, "status": "ok"}, {"name": "Lindenberger Nikolaus", "club": "WAT", "timeText": "1:16:39", "rank": 38, "timeS": 4599, "status": "ok"}, {"name": "Lyatoshinski Pavel", "club": "OLC Wienerwald", "timeText": "1:24:37", "rank": 39, "timeS": 5077, "status": "ok"}, {"name": "Wiesinger Simon", "club": "Naturfreunde Wien", "timeText": "1:35:16", "rank": 40, "timeS": 5716, "status": "ok"}, {"name": "Slateff Andreas", "club": "OLC Wienerwald", "timeText": "Fehlst", "status": "mp"}, {"name": "Kolar Hannes", "club": "Naturfreunde Wien", "timeText": "Disqu", "status": "dsq"}, {"name": "Kastner Nicolas", "club": "Naturfreunde Wien", "timeText": "N Ang", "status": "dns"}, {"name": "Wolfram Jakob", "club": "Naturfreunde Wien", "timeText": "N Ang", "status": "dns"}, {"name": "Poirson Marius", "club": "WAT", "timeText": "N Ang", "status": "dns"}, {"name": "Achilles Ingo", "club": "WAT", "timeText": "N Ang", "status": "dns"}, {"name": "Mayer Andreas", "club": "OLC Wienerwald", "timeText": "N Ang", "status": "dns"}], "courseLengthM": 4600, "courseClimbM": 200, "courseControls": 24}, {"name": "Herren -14 Wien", "declaredStarters": 8, "results": [{"name": "Jandl Florian", "club": "Naturfreunde Wien", "timeText": "12:55", "timeS": 775, "status": "ok", "rank": 1}, {"name": "Deubel Jonas", "club": "Naturfreunde Wien", "timeText": "15:24", "rank": 2, "timeS": 924, "status": "ok"}, {"name": "Altmann Benjamin", "club": "OLC Wienerwald", "timeText": "16:56", "rank": 3, "timeS": 1016, "status": "ok"}, {"name": "Gessl Konrad", "club": "WAT", "timeText": "17:04", "rank": 4, "timeS": 1024, "status": "ok"}, {"name": "Hnilica Hannes", "club": "OLT Transdanubien", "timeText": "17:23", "rank": 5, "timeS": 1043, "status": "ok"}, {"name": "Calvet Oliver", "club": "Naturfreunde Wien", "timeText": "21:56", "rank": 6, "timeS": 1316, "status": "ok"}, {"name": "Ditz Markus", "club": "Naturfreunde Wien", "timeText": "24:23", "rank": 7, "timeS": 1463, "status": "ok"}, {"name": "Leitner Mario", "club": "OLT Transdanubien", "timeText": "38:14", "rank": 8, "timeS": 2294, "status": "ok"}], "courseLengthM": 1600, "courseClimbM": 90, "courseControls": 9}, {"name": "Herren 45- Wien", "declaredStarters": 23, "results": [{"name": "Wittberger Georg", "club": "OLC Wienerwald", "timeText": "26:02", "timeS": 1562, "status": "ok", "rank": 1}, {"name": "Pietsch Wolfgang", "club": "Naturfreunde Wien", "timeText": "29:15", "rank": 2, "timeS": 1755, "status": "ok"}, {"name": "Gassner Ferri", "club": "Naturfreunde Wien", "timeText": "29:36", "rank": 3, "timeS": 1776, "status": "ok"}, {"name": "Zapletal Josef", "club": "Naturfreunde Wien", "timeText": "31:12", "rank": 4, "timeS": 1872, "status": "ok"}, {"name": "Täuber Thomas", "club": "OLT Transdanubien", "timeText": "31:37", "rank": 5, "timeS": 1897, "status": "ok"}, {"name": "Ditz Robert", "club": "Naturfreunde Wien", "timeText": "31:42", "rank": 6, "timeS": 1902, "status": "ok"}, {"name": "Lauri Pekka", "club": "Keravan Urheilijat", "timeText": "31:52", "rank": 7, "timeS": 1912, "status": "ok"}, {"name": "Hlosta Thomas", "club": "Naturfreunde Wien", "timeText": "32:21", "rank": 8, "timeS": 1941, "status": "ok"}, {"name": "Göschl Erich", "club": "OLC Wienerwald", "timeText": "32:32", "rank": 9, "timeS": 1952, "status": "ok"}, {"name": "Tiefenböck Willi", "club": "Naturfreunde Wien", "timeText": "33:31", "rank": 10, "timeS": 2011, "status": "ok"}, {"name": "Biel Axel", "club": "Naturfreunde Wien", "timeText": "35:01", "rank": 11, "timeS": 2101, "status": "ok"}, {"name": "Huemer Martin", "club": "WAT", "timeText": "36:59", "rank": 12, "timeS": 2219, "status": "ok"}, {"name": "Hofstätter Felix", "club": "Naturfreunde Wien", "timeText": "36:59", "rank": 12, "timeS": 2219, "status": "ok"}, {"name": "Kühnel Ralf", "club": "Naturfreunde Wien", "timeText": "37:21", "rank": 14, "timeS": 2241, "status": "ok"}, {"name": "Juraszovich Johannes", "club": "OLC Wienerwald", "timeText": "41:50", "rank": 15, "timeS": 2510, "status": "ok"}, {"name": "Wolfram Arnulf", "club": "WAT", "timeText": "47:24", "rank": 16, "timeS": 2844, "status": "ok"}, {"name": "Hilbert Josef", "club": "Naturfreunde Wien", "timeText": "48:20", "rank": 17, "timeS": 2900, "status": "ok"}, {"name": "Hampl Manfred", "club": "WATV", "timeText": "50:10", "rank": 18, "timeS": 3010, "status": "ok"}, {"name": "Huemer Thomas", "club": "WAT", "timeText": "52:13", "rank": 19, "timeS": 3133, "status": "ok"}, {"name": "Wiesinger Georg", "club": "Naturfreunde Wien", "timeText": "53:34", "rank": 20, "timeS": 3214, "status": "ok"}, {"name": "Skern Tim", "club": "Naturfreunde Wien", "timeText": "1:02:32", "rank": 21, "timeS": 3752, "status": "ok"}, {"name": "Kastner-Jirka Boris", "club": "Naturfreunde Wien", "timeText": "Aufg", "status": "dnf"}, {"name": "Deubel Dirk", "club": "Naturfreunde Wien", "timeText": "43:30", "timeS": 2610, "status": "ok", "outOfCompetition": true}], "courseLengthM": 3200, "courseClimbM": 160, "courseControls": 17}, {"name": "Herren 60- Wien", "declaredStarters": 14, "results": [{"name": "Huemer Meinrad", "club": "WAT", "timeText": "28:18", "timeS": 1698, "status": "ok", "rank": 1}, {"name": "Purgathofer Werner", "club": "OLG Ströck Wien", "timeText": "28:25", "rank": 2, "timeS": 1705, "status": "ok"}, {"name": "Dytlewski Nick", "club": "Naturfreunde Wien", "timeText": "31:38", "rank": 3, "timeS": 1898, "status": "ok"}, {"name": "Bonek Ernst", "club": "Naturfreunde Wien", "timeText": "32:01", "rank": 4, "timeS": 1921, "status": "ok"}, {"name": "Burmann Werner", "club": "OLC Wienerwald", "timeText": "34:18", "rank": 5, "timeS": 2058, "status": "ok"}, {"name": "Schuster Helmut", "club": "OLT Transdanubien", "timeText": "38:08", "rank": 6, "timeS": 2288, "status": "ok"}, {"name": "Kainzbauer Josef", "club": "WAT", "timeText": "38:44", "rank": 7, "timeS": 2324, "status": "ok"}, {"name": "Genevois Frédéric", "club": "Naturfreunde Wien", "timeText": "39:17", "rank": 8, "timeS": 2357, "status": "ok"}, {"name": "Siegert Reinhard", "club": "WAT", "timeText": "40:53", "rank": 9, "timeS": 2453, "status": "ok"}, {"name": "Kochmann Günther", "club": "WAT", "timeText": "46:23", "rank": 10, "timeS": 2783, "status": "ok"}, {"name": "Werther Wolf", "club": "WATV", "timeText": "48:58", "rank": 11, "timeS": 2938, "status": "ok"}, {"name": "Gassner Ferdinand", "club": "Naturfreunde Wien", "timeText": "1:11:16", "rank": 12, "timeS": 4276, "status": "ok"}, {"name": "Srb Walter", "club": "WAT", "timeText": "Aufg", "status": "dnf"}, {"name": "Radil Klaus", "club": "WAT", "timeText": "N Ang", "status": "dns"}], "courseLengthM": 2400, "courseClimbM": 145, "courseControls": 12}, {"name": "Damen -14 Wien", "declaredStarters": 8, "results": [{"name": "Tiefenböck Rita", "club": "Naturfreunde Wien", "timeText": "13:59", "timeS": 839, "status": "ok", "rank": 1}, {"name": "Hnilica Jana", "club": "OLT Transdanubien", "timeText": "17:07", "rank": 2, "timeS": 1027, "status": "ok"}, {"name": "Pietsch Anna", "club": "Naturfreunde Wien", "timeText": "18:02", "rank": 3, "timeS": 1082, "status": "ok"}, {"name": "Veitsberger Carina", "club": "OLT Transdanubien", "timeText": "19:08", "rank": 4, "timeS": 1148, "status": "ok"}, {"name": "Calvet Sofia", "club": "Naturfreunde Wien", "timeText": "19:26", "rank": 5, "timeS": 1166, "status": "ok"}, {"name": "Velkovski Julia", "club": "OLT Transdanubien", "timeText": "38:28", "rank": 6, "timeS": 2308, "status": "ok"}, {"name": "Kastner Maya", "club": "Naturfreunde Wien", "timeText": "N Ang", "status": "dns"}, {"name": "Ditz Carina", "club": "Naturfreunde Wien", "timeText": "N Ang", "status": "dns"}], "courseLengthM": 1600, "courseClimbM": 90, "courseControls": 9}, {"name": "Damen 45- Wien", "declaredStarters": 14, "results": [{"name": "Gollmann Birgit", "club": "Naturfreunde Wien", "timeText": "28:26", "timeS": 1706, "status": "ok", "rank": 1}, {"name": "Hnilica Sonja", "club": "OLT Transdanubien", "timeText": "31:02", "rank": 2, "timeS": 1862, "status": "ok"}, {"name": "Gassner Katja", "club": "Naturfreunde Wien", "timeText": "32:36", "rank": 3, "timeS": 1956, "status": "ok"}, {"name": "Palme Guni", "club": "OLC Wienerwald", "timeText": "33:43", "rank": 4, "timeS": 2023, "status": "ok"}, {"name": "Kastner Barbara", "club": "Naturfreunde Wien", "timeText": "34:33", "rank": 5, "timeS": 2073, "status": "ok"}, {"name": "Tiefenböck Riki", "club": "Naturfreunde Wien", "timeText": "37:34", "rank": 6, "timeS": 2254, "status": "ok"}, {"name": "Calvet Christine", "club": "Naturfreunde Wien", "timeText": "41:00", "rank": 7, "timeS": 2460, "status": "ok"}, {"name": "Pfeil Petra", "club": "Naturfreunde Wien", "timeText": "41:14", "rank": 8, "timeS": 2474, "status": "ok"}, {"name": "Wlcek Sonja", "club": "WAT", "timeText": "44:31", "rank": 9, "timeS": 2671, "status": "ok"}, {"name": "Lindenberger Doris", "club": "WAT", "timeText": "49:32", "rank": 10, "timeS": 2972, "status": "ok"}, {"name": "Hilbert Sabine", "club": "Naturfreunde Wien", "timeText": "51:23", "rank": 11, "timeS": 3083, "status": "ok"}, {"name": "Pietsch-Grabner Jutta", "club": "Naturfreunde Wien", "timeText": "54:56", "rank": 12, "timeS": 3296, "status": "ok"}, {"name": "Pietsch Silvia", "club": "Naturfreunde Wien", "timeText": "1:02:47", "rank": 13, "timeS": 3767, "status": "ok"}, {"name": "Wolfram-Teischl Sabine", "club": "Naturfreunde Wien", "timeText": "N Ang", "status": "dns"}], "courseLengthM": 2400, "courseClimbM": 145, "courseControls": 12}, {"name": "Damen 55- Wien", "declaredStarters": 4, "results": [{"name": "Broinger Karin", "club": "OLC Wienerwald", "timeText": "37:04", "rank": 1, "timeS": 2224, "status": "ok"}, {"name": "Bonek Anneliese", "club": "Naturfreunde Wien", "timeText": "42:11", "rank": 2, "timeS": 2531, "status": "ok"}, {"name": "Kienast Johanna", "club": "OLT Transdanubien", "timeText": "N Ang", "status": "dns"}, {"name": "Pamlitschka Herta", "club": "WAT", "timeText": "N Ang", "status": "dns"}], "courseLengthM": 2000, "courseClimbM": 110, "courseControls": 12}, {"name": "Neulinge", "declaredStarters": 10, "results": [{"name": "Mittendorfer Roman", "club": "Vereinslos (no club)", "timeText": "14:12", "rank": 1, "timeS": 852, "status": "ok"}, {"name": "Radon Livia", "club": "Naturfreunde Wien", "timeText": "21:13", "rank": 2, "timeS": 1273, "status": "ok"}, {"name": "Schwarz Andrea", "club": "Vereinslos (no club)", "timeText": "24:39", "rank": 3, "timeS": 1479, "status": "ok"}, {"name": "Radon Zoe", "club": "Naturfreunde Wien", "timeText": "26:32", "rank": 4, "timeS": 1592, "status": "ok"}, {"name": "Müller Irene", "club": "vereinslos", "timeText": "33:49", "rank": 5, "timeS": 2029, "status": "ok"}, {"name": "Schlögl Richard", "club": "Naturfreunde Wien", "timeText": "35:59", "rank": 6, "timeS": 2159, "status": "ok"}, {"name": "Beck Maria", "club": "Naturfreunde Wien", "timeText": "51:35", "rank": 7, "timeS": 3095, "status": "ok"}, {"name": "Strangl Susanne", "club": "Vereinslos (no club)", "timeText": "56:57", "rank": 8, "timeS": 3417, "status": "ok"}, {"name": "Kapeller Gabriele", "club": "Vereinslos (no club)", "timeText": "57:00", "rank": 9, "timeS": 3420, "status": "ok"}, {"name": "Punzet Lena", "club": "Vereinslos (no club)", "timeText": "1:01:15", "rank": 10, "timeS": 3675, "status": "ok", "resultKind": "pair", "note": "Partner: Punzet Julianna"}, {"name": "Punzet Julianna", "club": "Vereinslos (no club)", "timeText": "1:01:15", "rank": 10, "timeS": 3675, "status": "ok", "resultKind": "pair", "note": "Partner: Punzet Lena"}], "courseLengthM": 1400, "courseClimbM": 70, "courseControls": 5}, {"name": "Offen Kurz", "declaredStarters": 18, "results": [{"name": "Heindl Monika", "club": "Orienteering Klosterneuburg", "timeText": "24:00", "rank": 1, "timeS": 1440, "status": "ok"}, {"name": "Grünbeck Johannes", "club": "OLC Wienerwald", "timeText": "25:06", "rank": 2, "timeS": 1506, "status": "ok"}, {"name": "Glentzer Nina", "club": "WAT", "timeText": "27:27", "rank": 3, "timeS": 1647, "status": "ok"}, {"name": "Schuster Bianca", "club": "OLT Transdanubien", "timeText": "27:41", "rank": 4, "timeS": 1661, "status": "ok"}, {"name": "Stift Pia", "club": "PSV", "timeText": "29:28", "rank": 5, "timeS": 1768, "status": "ok"}, {"name": "Stift Beate", "club": "Vereinslos (no club)", "timeText": "29:32", "rank": 6, "timeS": 1772, "status": "ok"}, {"name": "Hiebl Carmen", "club": "HSV OL Wiener Neustadt", "timeText": "30:13", "rank": 7, "timeS": 1813, "status": "ok"}, {"name": "Nesitka Doris", "club": "vereinslos", "timeText": "31:32", "rank": 8, "timeS": 1892, "status": "ok"}, {"name": "Hennecker Hermine", "club": "HSV OL Wiener Neustadt", "timeText": "32:13", "rank": 9, "timeS": 1933, "status": "ok"}, {"name": "Schiel Doris", "club": "OLC Wienerwald", "timeText": "34:42", "rank": 10, "timeS": 2082, "status": "ok"}, {"name": "Schuster Manuela", "club": "OLT Transdanubien", "timeText": "36:20", "rank": 11, "timeS": 2180, "status": "ok"}, {"name": "Hilty Lea", "club": "Vereinslos (no club)", "timeText": "41:35", "rank": 12, "timeS": 2495, "status": "ok"}, {"name": "Scharwath Birgitt", "club": "vereinslos", "timeText": "45:18", "rank": 13, "timeS": 2718, "status": "ok"}, {"name": "Jonackova Zuzana", "club": "OLT Transdanubien", "timeText": "47:08", "rank": 14, "timeS": 2828, "status": "ok"}, {"name": "Schinnerer Petra", "club": "Wr. Gehörlosen Sportclub 190", "timeText": "147:59", "rank": 15, "timeS": 8879, "status": "ok"}, {"name": "Jeschko Sabine", "club": "Vereinslos (no club)", "timeText": "50:39", "rank": 16, "timeS": 3039, "status": "ok"}, {"name": "Stift Martin", "club": "PSV", "timeText": "Fehlst", "status": "mp"}, {"name": "Zezulka Marion", "club": "HSV Großmittel", "timeText": "N Ang", "status": "dns"}], "courseLengthM": 2000, "courseClimbM": 100, "courseControls": 12}, {"name": "Offen Lang", "declaredStarters": 18, "results": [{"name": "Schiel Philipp", "club": "OLC Graz", "timeText": "26:51", "rank": 1, "timeS": 1611, "status": "ok"}, {"name": "Lang Karl", "club": "HSV Pinkafeld", "timeText": "35:15", "rank": 2, "timeS": 2115, "status": "ok"}, {"name": "Samek Fabian", "club": "WAT", "timeText": "37:13", "rank": 3, "timeS": 2233, "status": "ok"}, {"name": "Pfeffer Martin", "club": "vereinslos", "timeText": "37:15", "rank": 4, "timeS": 2235, "status": "ok"}, {"name": "Kaliwoda Ernst", "club": "WAT", "timeText": "37:47", "rank": 5, "timeS": 2267, "status": "ok"}, {"name": "Schiel Herbert", "club": "OLC Wienerwald", "timeText": "38:59", "rank": 6, "timeS": 2339, "status": "ok"}, {"name": "Rochford Iain", "club": "OC Fürstenfeld", "timeText": "39:26", "rank": 7, "timeS": 2366, "status": "ok"}, {"name": "Bednarikova Tatiana", "club": "TJ Cingov Spisska Nova Ves", "timeText": "53:36", "rank": 8, "timeS": 3216, "status": "ok"}, {"name": "Grassinger Helmut", "club": "vereinslos", "timeText": "53:45", "rank": 9, "timeS": 3225, "status": "ok"}, {"name": "Schinnerer Florian", "club": "OLG Ströck Wien", "timeText": "54:18", "rank": 10, "timeS": 3258, "status": "ok"}, {"name": "Hoch Gabi", "club": "Naturfreunde Steiermark", "timeText": "56:26", "rank": 11, "timeS": 3386, "status": "ok"}, {"name": "Hailing Markus", "club": "Naturfreunde Steiermark", "timeText": "58:35", "rank": 12, "timeS": 3515, "status": "ok"}, {"name": "Peroutka Jarek", "club": "HSV OL Wiener Neustadt", "timeText": "1:02:50", "rank": 13, "timeS": 3770, "status": "ok"}, {"name": "Zezulka Markus", "club": "HSV Großmittel", "timeText": "1:22:12", "rank": 14, "timeS": 4932, "status": "ok"}, {"name": "Anderle Christian", "club": "Vereinslos (no club)", "timeText": "1:26:20", "rank": 15, "timeS": 5180, "status": "ok"}, {"name": "Kracker Martin", "club": "Naturfreunde Wien", "timeText": "1:31:55", "rank": 16, "timeS": 5515, "status": "ok"}, {"name": "Gschöpf Brie", "club": "WAT", "timeText": "1:34:35", "rank": 17, "timeS": 5675, "status": "ok"}, {"name": "Guggenberger David", "club": "Naturfreunde Wien", "timeText": "N Ang", "status": "dns"}], "courseLengthM": 3400, "courseClimbM": 190, "courseControls": 18}]}