{"eventId": 3505, "source": "sportsoftware-pdf", "sourceUrl": "https://anne-cdn.oefol.at/public/legacy/event_3505_results-long.pdf", "fileName": "event_3505_results-long.pdf", "listType": "race", "docDate": null, "categories": [{"name": "M -12", "declaredStarters": 5, "results": [{"name": "Daniel Szabó Klub OB", "club": "Sokol Pezinok", "timeText": "32:11", "rank": 1, "timeS": 1931, "status": "ok"}]}, {"name": "M -14", "declaredStarters": 10, "results": [{"name": "Matej Jendek Klub OB", "club": "Sokol Pezinok", "timeText": "141:10", "rank": 9, "timeS": 8470, "status": "ok"}, {"name": "Ondrej Jendek Klub OB", "club": "Sokol Pezinok", "timeText": "146:51", "rank": 10, "timeS": 8811, "status": "ok"}]}, {"name": "M -16", "declaredStarters": 4, "results": [{"name": "Ján Kuchárik Klub OB", "club": "Sokol Pezinok", "timeText": "81:05", "rank": 3, "timeS": 4865, "status": "ok"}]}, {"name": "M 19-", "declaredStarters": 15, "results": [{"name": "Ondrej Piják", "club": "Kobra Bratislava", "timeText": "69:52", "rank": 2, "timeS": 4192, "status": "ok"}, {"name": "Oliver Lago", "club": "ŠK VAZKA Bratislava", "timeText": "96:25", "rank": 8, "timeS": 5785, "status": "ok"}, {"name": "Miroslav Lago", "club": "ŠK VAZKA Bratislava", "timeText": "113:18", "rank": 11, "timeS": 6798, "status": "ok"}, {"name": "Peter Karch Klub OB", "club": "Sokol Pezinok", "timeText": "117:27", "rank": 13, "timeS": 7047, "status": "ok"}, {"name": "Juraj Horniak", "club": "Kobra Bratislava", "timeText": "MP", "status": "mp"}]}, {"name": "M 40-", "declaredStarters": 15, "results": [{"name": "Peter Mlynárik", "club": "ŠK VAZKA Bratislava", "timeText": "68:27", "rank": 2, "timeS": 4107, "status": "ok"}, {"name": "Rostislav Navrátil", "club": "ŠK VAZKA Bratislava", "timeText": "69:17", "rank": 3, "timeS": 4157, "status": "ok"}]}, {"name": "MeOS 2021-11-06 18:46:41, M 40-,", "declaredStarters": 2, "results": [{"name": "Michal Pavelek Klub OB", "club": "Sokol Pezinok", "timeText": "86:59", "rank": 7, "timeS": 5219, "status": "ok"}, {"name": "Róbert Schenk", "club": "TJ Rapid Bratislava", "timeText": "110:30", "rank": 12, "timeS": 6630, "status": "ok"}]}, {"name": "M 55-", "declaredStarters": 12, "results": [{"name": "Jozef Fedor Klub OB", "club": "Sokol Pezinok", "timeText": "84:12", "rank": 4, "timeS": 5052, "status": "ok"}, {"name": "Milan Petrinec", "club": "TJ Rapid Bratislava", "timeText": "MP", "status": "mp"}]}, {"name": "W -14", "declaredStarters": 9, "results": [{"name": "Lucia Syrová Klub OB", "club": "Sokol Pezinok", "timeText": "67:34", "rank": 7, "timeS": 4054, "status": "ok"}, {"name": "Sara Sensi", "club": "GAMČA", "timeText": "80:04", "rank": 9, "timeS": 4804, "status": "ok"}]}, {"name": "W -16", "declaredStarters": 4, "results": [{"name": "Elena Lago", "club": "ŠK VAZKA Bratislava", "timeText": "100:39", "rank": 4, "timeS": 6039, "status": "ok"}]}, {"name": "W 19-", "declaredStarters": 11, "results": [{"name": "Katarína Fedorová Klub OB", "club": "Sokol Pezinok", "timeText": "76:07", "rank": 2, "timeS": 4567, "status": "ok"}, {"name": "Barbora Pijáková Klub OB", "club": "Sokol Pezinok", "timeText": "76:27", "rank": 3, "timeS": 4587, "status": "ok"}, {"name": "Adéla Navrátilová", "club": "ŠK VAZKA Bratislava", "timeText": "113:17", "rank": 7, "timeS": 6797, "status": "ok"}]}, {"name": "W 40-", "declaredStarters": 12, "results": [{"name": "Martina Pánková", "club": "TJ Rapid Bratislava", "timeText": "87:45", "rank": 2, "timeS": 5265, "status": "ok"}, {"name": "Katarína Schenková", "club": "TJ Rapid Bratislava", "timeText": "91:43", "rank": 4, "timeS": 5503, "status": "ok"}, {"name": "Eva Marková", "club": "Kobra Bratislava", "timeText": "126:59", "rank": 7, "timeS": 7619, "status": "ok"}, {"name": "Svelana Puls", "club": "TJ Rapid Bratislava", "timeText": "MP", "status": "mp"}]}, {"name": "W 55-", "declaredStarters": 6, "results": [{"name": "Beata Vávrová", "club": "TJ Rapid Bratislava", "timeText": "DNF", "status": "dnf"}]}, {"name": "W -10", "declaredStarters": 4, "results": [{"name": "Nela Urbanczyková", "club": "ŠK VAZKA Bratislava", "timeText": "25:27", "rank": 1, "timeS": 1527, "status": "ok"}]}, {"name": "N", "declaredStarters": 13, "results": [{"name": "Amália Repová", "club": "GAMČA", "timeText": "49:30", "rank": 2, "timeS": 2970, "status": "ok"}]}, {"name": "MW-R", "declaredStarters": 9, "results": [{"name": "Ella Mária Petrincová", "club": "Kobra Bratislava", "timeText": "24:48", "rank": 1, "timeS": 1488, "status": "ok"}]}, {"name": "Open", "declaredStarters": 16, "results": [{"name": "Kilian Jörg", "club": "OLC Wienerwald", "timeText": "44:06", "rank": 1, "timeS": 2646, "status": "ok"}, {"name": "Veronika Vachova Klub OB", "club": "Sokol Pezinok", "timeText": "54:30", "rank": 3, "timeS": 3270, "status": "ok"}, {"name": "Lenka Jablonovská Klub OB", "club": "Sokol Pezinok", "timeText": "57:05", "rank": 4, "timeS": 3425, "status": "ok"}, {"name": "Adam Navrátil", "club": "ŠK VAZKA Bratislava", "timeText": "103:16", "rank": 9, "timeS": 6196, "status": "ok"}, {"name": "Franz Kaiser", "club": "OLCU Viktring", "timeText": "104:32", "rank": 10, "timeS": 6272, "status": "ok"}, {"name": "Valerie Rymarz No", "club": "club", "timeText": "135:00", "rank": 12, "timeS": 8100, "status": "ok"}, {"name": "Johannes Mach", "club": "Go Harzberg", "timeText": "DNF", "status": "dnf"}, {"name": "Kathrin Kollndorfer", "club": "HSV Großmittel", "timeText": "DNF", "status": "dnf"}]}, {"name": "H/D14", "declaredStarters": 4, "results": [{"name": "Niklas Ochenbauer", "club": "HSV OL Wiener Neustadt", "timeText": "24:17", "rank": 1, "timeS": 1457, "status": "ok"}, {"name": "Jonas Ochenbauer", "club": "HSV OL Wiener Neustadt", "timeText": "37:45", "rank": 2, "timeS": 2265, "status": "ok"}, {"name": "Angelina Ochenbauer", "club": "HSV OL Wiener Neustadt", "timeText": "40:48", "rank": 3, "timeS": 2448, "status": "ok"}, {"name": "Peo Adenstedt", "club": "Orienteering Klosterneuburg", "timeText": "41:11", "rank": 4, "timeS": 2471, "status": "ok"}]}, {"name": "H19", "declaredStarters": 8, "results": [{"name": "Markus Plohn", "club": "HSV OL Wiener Neustadt", "timeText": "77:18", "rank": 1, "timeS": 4638, "status": "ok"}, {"name": "Pierre Kaltenbacher", "club": "HSV OL Wiener Neustadt", "timeText": "78:42", "rank": 2, "timeS": 4722, "status": "ok"}, {"name": "Daniel Bichl", "club": "WAT-OL", "timeText": "87:37", "rank": 3, "timeS": 5257, "status": "ok"}, {"name": "Dominik Lapornik", "club": "HSV Großmittel", "timeText": "89:44", "rank": 4, "timeS": 5384, "status": "ok"}, {"name": "Marius Poirson", "club": "WAT-OL", "timeText": "92:15", "rank": 5, "timeS": 5535, "status": "ok"}, {"name": "Nikolaus Euler-Rolle", "club": "Naturfreunde Wien", "timeText": "97:14", "rank": 6, "timeS": 5834, "status": "ok"}, {"name": "Thomas Fabian", "club": "WAT-OL", "timeText": "120:31", "rank": 7, "timeS": 7231, "status": "ok"}, {"name": "Matthias Poell", "club": "OLC Wienerwald", "timeText": "139:11", "rank": 8, "timeS": 8351, "status": "ok"}]}, {"name": "H35", "declaredStarters": 2, "results": [{"name": "Fabian Samec", "club": "WAT-OL", "timeText": "80:17", "rank": 1, "timeS": 4817, "status": "ok"}, {"name": "Samuel Imriska", "club": "Naturfreunde Wien", "timeText": "85:25", "rank": 2, "timeS": 5125, "status": "ok"}]}, {"name": "H45", "declaredStarters": 6, "results": [{"name": "Michael Stockmayer", "club": "HSV OL Wiener Neustadt", "timeText": "56:31", "rank": 1, "timeS": 3391, "status": "ok"}, {"name": "Georg Wittberger", "club": "HSV OL Wiener Neustadt", "timeText": "71:34", "rank": 2, "timeS": 4294, "status": "ok"}, {"name": "Pekka Lauri", "club": "Keravan Urheilijat (FIN)", "timeText": "78:30", "rank": 3, "timeS": 4710, "status": "ok"}, {"name": "Roland Reisenberger", "club": "Orienteering Klosterneuburg", "timeText": "78:53", "rank": 4, "timeS": 4733, "status": "ok"}, {"name": "Werner Kugler", "club": "WAT-OL", "timeText": "140:47", "rank": 5, "timeS": 8447, "status": "ok"}, {"name": "Harald Lipphart-Kirchmeir", "club": "HSV OL Wiener Neustadt", "timeText": "DNF", "status": "dnf"}]}, {"name": "H55", "declaredStarters": 5, "results": [{"name": "Josef Zapletal", "club": "Naturfreunde Wien", "timeText": "54:43", "rank": 1, "timeS": 3283, "status": "ok"}, {"name": "Martin Grünberger", "club": "Orienteering Klosterneuburg", "timeText": "60:57", "rank": 2, "timeS": 3657, "status": "ok"}, {"name": "Nikolaus Adenstedt", "club": "Orienteering Klosterneuburg", "timeText": "83:55", "rank": 3, "timeS": 5035, "status": "ok"}, {"name": "Hannes Rotheneder", "club": "HSV Großmittel", "timeText": "97:42", "rank": 4, "timeS": 5862, "status": "ok"}, {"name": "Herbert Kanai", "club": "HSV OL Wiener Neustadt", "timeText": "106:30", "rank": 5, "timeS": 6390, "status": "ok"}]}, {"name": "H65", "declaredStarters": 5, "results": [{"name": "Josef Hones", "club": "HSV Ried", "timeText": "46:23", "rank": 1, "timeS": 2783, "status": "ok"}, {"name": "Valentin Pidner", "club": "HSV OL Wiener Neustadt", "timeText": "50:10", "rank": 2, "timeS": 3010, "status": "ok"}, {"name": "Hubert Lukaseder", "club": "HSV Langenlebarn", "timeText": "50:41", "rank": 3, "timeS": 3041, "status": "ok"}, {"name": "Franz Ponweiser", "club": "HSV OL Wiener Neustadt", "timeText": "53:03", "rank": 4, "timeS": 3183, "status": "ok"}, {"name": "Reinhard Siegert", "club": "WAT-OL", "timeText": "90:50", "rank": 5, "timeS": 5450, "status": "ok"}]}, {"name": "D45", "declaredStarters": 1, "results": [{"name": "Guni Palme", "club": "OLC Wienerwald", "timeText": "73:29", "rank": 1, "timeS": 4409, "status": "ok"}]}, {"name": "D55", "declaredStarters": 6, "results": [{"name": "Ingrid Adenstedt", "club": "Orienteering Klosterneuburg", "timeText": "45:49", "rank": 1, "timeS": 2749, "status": "ok"}, {"name": "Nicole Ochenbauer", "club": "HSV OL Wiener Neustadt", "timeText": "45:50", "rank": 2, "timeS": 2750, "status": "ok"}, {"name": "Elisabeth Kirchmeir", "club": "HSV OL Wiener Neustadt", "timeText": "50:36", "rank": 3, "timeS": 3036, "status": "ok"}, {"name": "Fiorella Kaiser", "club": "OLCU Viktring", "timeText": "65:53", "rank": 4, "timeS": 3953, "status": "ok"}, {"name": "Hannelore Schreiber", "club": "HSV Langenlebarn", "timeText": "68:41", "rank": 5, "timeS": 4121, "status": "ok"}, {"name": "Roswitha Micko", "club": "OLC Wienerwald", "timeText": "82:02", "rank": 6, "timeS": 4922, "status": "ok"}]}, {"name": "D65", "declaredStarters": 3, "results": [{"name": "Elisabeth Knapp", "club": "Orienteering Klosterneuburg", "timeText": "46:03", "rank": 1, "timeS": 2763, "status": "ok"}, {"name": "Reingild Linhart", "club": "HSV OL Wiener Neustadt", "timeText": "52:31", "rank": 2, "timeS": 3151, "status": "ok"}, {"name": "Christine Ponweiser", "club": "HSV OL Wiener Neustadt", "timeText": "75:55", "rank": 3, "timeS": 4555, "status": "ok"}]}, {"name": "Kind m. Begleit.", "declaredStarters": 2, "results": [{"name": "Tobias Kaltenbacher", "club": "HSV OL Wiener Neustadt", "timeText": "19:09", "rank": 1, "timeS": 1149, "status": "ok"}]}, {"name": "Neulinge", "declaredStarters": 6, "results": [{"name": "Sabrina Bühn No", "club": "club", "timeText": "45:42", "rank": 1, "timeS": 2742, "status": "ok"}, {"name": "Beatrix Micheli", "club": "vereinslos", "timeText": "55:44", "rank": 2, "timeS": 3344, "status": "ok"}, {"name": "Anna Haider", "club": "HSV Ried", "timeText": "57:21", "rank": 3, "timeS": 3441, "status": "ok"}, {"name": "Manuela Peneder", "club": "vereinslos", "timeText": "71:28", "rank": 4, "timeS": 4288, "status": "ok"}, {"name": "Richard Lederer", "club": "WAT-OL", "timeText": "MP", "status": "mp"}, {"name": "Heinz Czembirek", "club": "MTV Hernals", "timeText": "DNS", "status": "dns"}]}]}