{"eventId": 4114, "source": "sportsoftware-pdf", "sourceUrl": "https://anne-cdn.oefol.at/public/legacy/event_4114_ergebnis-5-ac-2023.pdf", "fileName": "event_4114_ergebnis-5-ac-2023.pdf", "listType": "race", "docDate": "2023-07-03", "categories": [{"name": "Herren ab 21 Elite", "declaredStarters": 26, "results": [{"name": "Bonek Jannis", "club": "Naturfreunde Wien", "timeText": "13:09", "sourceBib": "555", "sourceNat": "AUT", "rank": 1, "timeS": 789, "status": "ok"}, {"name": "Kastner Nicolas", "club": "Naturfreunde Wien", "timeText": "13:51", "sourceBib": "526", "sourceNat": "AUT", "rank": 2, "timeS": 831, "status": "ok"}, {"name": "Reiner Matthias", "club": "Naturfreunde Villach - Oriente", "timeText": "14:07", "sourceBib": "147", "sourceNat": "- Oriente AUT", "rank": 3, "timeS": 847, "status": "ok"}, {"name": "Novak Lukas", "club": "Leibnitzer AC OLG", "timeText": "14:28", "sourceBib": "334", "sourceNat": "AUT", "rank": 4, "timeS": 868, "status": "ok"}, {"name": "Gröll Matthias", "club": "OLC Graz", "timeText": "14:43", "sourceBib": "347", "sourceNat": "AUT", "rank": 5, "timeS": 883, "status": "ok"}, {"name": "Peter Mathias", "club": "OLC Graz", "timeText": "14:49", "sourceBib": "355", "sourceNat": "AUT", "rank": 6, "timeS": 889, "status": "ok"}, {"name": "Ymsén Gernot", "club": "HSV Pinkafeld", "timeText": "14:50", "sourceBib": "105", "sourceNat": "AUT", "rank": 7, "timeS": 890, "status": "ok"}, {"name": "Gröll Georg", "club": "OLC Graz", "timeText": "15:20", "sourceBib": "368", "sourceNat": "AUT", "rank": 8, "timeS": 920, "status": "ok"}, {"name": "Kurz Florian", "club": "Naturfreunde Wien", "timeText": "15:30", "sourceBib": "541", "sourceNat": "AUT", "rank": 9, "timeS": 930, "status": "ok"}, {"name": "Binder Martin", "club": "SU Klagenfurt", "timeText": "15:47", "sourceBib": "164", "sourceNat": "AUT", "rank": 10, "timeS": 947, "status": "ok"}, {"name": "Wolfram Jakob", "club": "Naturfreunde Wien", "timeText": "15:51", "sourceBib": "558", "sourceNat": "AUT", "rank": 11, "timeS": 951, "status": "ok"}, {"name": "Schiel Philipp", "club": "OLC Graz", "timeText": "16:09", "sourceBib": "345", "sourceNat": "AUT", "rank": 12, "timeS": 969, "status": "ok"}, {"name": "Leonhardt Matthias", "club": "OC Fürstenfeld", "timeText": "16:15", "sourceBib": "407", "sourceNat": "AUT", "rank": 13, "timeS": 975, "status": "ok"}, {"name": "Zapf Kilian", "club": "OC Fürstenfeld", "timeText": "16:21", "sourceBib": "419", "sourceNat": "AUT", "rank": 14, "timeS": 981, "status": "ok"}, {"name": "Wendner Christoph", "club": "SU Schöckl Orienteering", "timeText": "16:25", "sourceBib": "388", "sourceNat": "AUT", "rank": 15, "timeS": 985, "status": "ok"}, {"name": "Trummer Kilian", "club": "OLC Graz", "timeText": "16:26", "sourceBib": "348", "sourceNat": "AUT", "rank": 16, "timeS": 986, "status": "ok"}, {"name": "Bonek Erik", "club": "Naturfreunde Wien", "timeText": "16:35", "sourceBib": "554", "sourceNat": "AUT", "rank": 17, "timeS": 995, "status": "ok"}, {"name": "Friedrichs Bjarne", "club": "ASKÖ Henndorf Orienteering", "timeText": "16:42", "sourceBib": "292", "sourceNat": "AUT", "rank": 18, "timeS": 1002, "status": "ok"}, {"name": "Simkovics Erik", "club": "OLC Wienerwald", "timeText": "17:11", "sourceBib": "594", "sourceNat": "AUT", "rank": 19, "timeS": 1031, "status": "ok"}, {"name": "Ebster Leon", "club": "ASKÖ Henndorf Orienteering", "timeText": "17:26", "sourceBib": "310", "sourceNat": "AUT", "rank": 20, "timeS": 1046, "status": "ok"}, {"name": "Gremmel Richard", "club": "HSV Pinkafeld", "timeText": "18:08", "sourceBib": "329", "sourceNat": "AUT", "rank": 21, "timeS": 1088, "status": "ok"}, {"name": "Pauser Jakob", "club": "HSV OL Wiener Neustadt", "timeText": "18:17", "sourceBib": "207", "sourceNat": "AUT", "rank": 22, "timeS": 1097, "status": "ok"}, {"name": "Sturm Gregor", "club": "Orienteering Innsbruck Imst", "timeText": "19:28", "sourceBib": "475", "sourceNat": "Imst AUT", "rank": 23, "timeS": 1168, "status": "ok"}, {"name": "Mayr Bernhard", "club": "HSV Absam OL", "timeText": "19:55", "sourceBib": "432", "sourceNat": "AUT", "rank": 24, "timeS": 1195, "status": "ok"}, {"name": "Teichmann Tobias", "club": "SU Schöckl Orienteering", "timeText": "28:10", "sourceBib": "373", "sourceNat": "AUT", "rank": 25, "timeS": 1690, "status": "ok"}, {"name": "Holper Leo", "club": "OC Fürstenfeld", "timeText": "N Ang", "sourceBib": "420", "sourceNat": "AUT", "status": "dns"}], "courseLengthM": 3900, "courseClimbM": 125, "courseControls": 21}, {"name": "Herren bis 20 Elite", "declaredStarters": 8, "results": [{"name": "Tobler Simon", "club": "HSV Pinkafeld", "timeText": "12:48", "sourceBib": "108", "sourceNat": "AUT", "rank": 1, "timeS": 768, "status": "ok"}, {"name": "Czech Moritz", "club": "Orienteering Klosterneuburg", "timeText": "13:03", "sourceBib": "231", "sourceNat": "AUT", "rank": 2, "timeS": 783, "status": "ok"}, {"name": "Wieser Lukas", "club": "HSV Pinkafeld", "timeText": "13:10", "sourceBib": "109", "sourceNat": "AUT", "rank": 3, "timeS": 790, "status": "ok"}, {"name": "Buschek Anton", "club": "Naturfreunde Wien", "timeText": "13:36", "sourceBib": "570", "sourceNat": "AUT", "rank": 4, "timeS": 816, "status": "ok"}, {"name": "Greiner Gustav", "club": "SU Schöckl Orienteering", "timeText": "13:40", "sourceBib": "374", "sourceNat": "AUT", "rank": 5, "timeS": 820, "status": "ok"}, {"name": "Rapotz David", "club": "Naturfreunde Villach - Oriente", "timeText": "13:48", "sourceBib": "144", "sourceNat": "- Oriente AUT", "rank": 6, "timeS": 828, "status": "ok"}, {"name": "Prutsch Joel", "club": "OC Fürstenfeld", "timeText": "14:04", "sourceBib": "399", "sourceNat": "AUT", "rank": 7, "timeS": 844, "status": "ok"}, {"name": "Brabek Peter", "club": "OC Fürstenfeld", "timeText": "Disqu", "sourceBib": "422", "sourceNat": "AUT", "status": "dsq"}], "courseLengthM": 3300, "courseClimbM": 125, "courseControls": 20}, {"name": "Herren bis 18 Elite", "declaredStarters": 8, "results": [{"name": "Stöcher Jacopo", "club": "WAT-OL", "timeText": "13:24", "sourceBib": "627", "sourceNat": "AUT", "rank": 1, "timeS": 804, "status": "ok"}, {"name": "Monsberger Elias", "club": "OC Fürstenfeld", "timeText": "14:39", "sourceBib": "421", "sourceNat": "AUT", "rank": 2, "timeS": 879, "status": "ok"}, {"name": "Rass Maximilian", "club": "Orienteering Innsbruck Imst", "timeText": "15:16", "sourceBib": "468", "sourceNat": "Imst AUT", "rank": 3, "timeS": 916, "status": "ok"}, {"name": "Greiner Moritz", "club": "SU Schöckl Orienteering", "timeText": "15:52", "sourceBib": "382", "sourceNat": "AUT", "rank": 4, "timeS": 952, "status": "ok"}, {"name": "Reicher Paul", "club": "OLC Graz", "timeText": "16:22", "sourceBib": "352", "sourceNat": "AUT", "rank": 5, "timeS": 982, "status": "ok"}, {"name": "Dobler Theo", "club": "MTV Hernals", "timeText": "16:26", "sourceBib": "513", "sourceNat": "AUT", "rank": 6, "timeS": 986, "status": "ok"}, {"name": "Ballik Simon", "club": "WAT-OL", "timeText": "18:42", "sourceBib": "630", "sourceNat": "AUT", "rank": 7, "timeS": 1122, "status": "ok"}, {"name": "Gidl Florian", "club": "Orienteering Innsbruck Imst", "timeText": "21:22", "sourceBib": "444", "sourceNat": "Imst AUT", "rank": 8, "timeS": 1282, "status": "ok"}], "courseLengthM": 3300, "courseClimbM": 125, "courseControls": 20}, {"name": "Herren bis 16 Elite", "declaredStarters": 15, "results": [{"name": "Ochenbauer Niklas", "club": "HSV OL Wiener Neustadt", "timeText": "11:35", "sourceBib": "206", "sourceNat": "AUT", "rank": 1, "timeS": 695, "status": "ok"}, {"name": "Schnepf Oliver", "club": "OC Fürstenfeld", "timeText": "11:44", "sourceBib": "395", "sourceNat": "AUT", "rank": 2, "timeS": 704, "status": "ok"}, {"name": "Nindl Maximilian", "club": "Naturfreunde Kitzbühel", "timeText": "12:39", "sourceBib": "500", "sourceNat": "AUT", "rank": 3, "timeS": 759, "status": "ok"}, {"name": "Angermann Tobias", "club": "SU Klagenfurt", "timeText": "12:53", "sourceBib": "160", "sourceNat": "AUT", "rank": 4, "timeS": 773, "status": "ok"}, {"name": "Meizer Jonas", "club": "SU Klagenfurt", "timeText": "12:53", "sourceBib": "169", "sourceNat": "AUT", "rank": 4, "timeS": 773, "status": "ok"}, {"name": "Adenstedt Peo", "club": "Orienteering Klosterneuburg", "timeText": "13:13", "sourceBib": "224", "sourceNat": "AUT", "rank": 6, "timeS": 793, "status": "ok"}, {"name": "Frohner Lukas", "club": "FUN-OL NÖ", "timeText": "13:44", "sourceBib": "664", "sourceNat": "AUT", "rank": 7, "timeS": 824, "status": "ok"}, {"name": "Davitt James", "club": "Naturfreunde Wien", "timeText": "13:54", "sourceBib": "557", "sourceNat": "AUT", "rank": 8, "timeS": 834, "status": "ok"}, {"name": "Perktold David", "club": "Orienteering Innsbruck Imst", "timeText": "14:30", "sourceBib": "463", "sourceNat": "Imst AUT", "rank": 9, "timeS": 870, "status": "ok"}, {"name": "Hinterplattner Nikolaus", "club": "MTV Hernals", "timeText": "15:44", "sourceBib": "511", "sourceNat": "AUT", "rank": 10, "timeS": 944, "status": "ok"}, {"name": "Houdek Felix", "club": "OC Fürstenfeld", "timeText": "16:52", "sourceBib": "412", "sourceNat": "AUT", "rank": 11, "timeS": 1012, "status": "ok"}, {"name": "Scheuer Lukas", "club": "OC Fürstenfeld", "timeText": "18:24", "sourceBib": "410", "sourceNat": "AUT", "rank": 12, "timeS": 1104, "status": "ok"}, {"name": "Kolar Fabian", "club": "Naturfreunde Wien", "timeText": "18:40", "sourceBib": "531", "sourceNat": "AUT", "rank": 13, "timeS": 1120, "status": "ok"}, {"name": "Begh Julian", "club": "OC Fürstenfeld", "timeText": "Fehlst", "sourceBib": "411", "sourceNat": "AUT", "status": "mp"}, {"name": "Fischerleitner Clemens", "club": "HSV Ried", "timeText": "N Ang", "sourceBib": "246", "sourceNat": "AUT", "status": "dns"}], "courseLengthM": 2500, "courseClimbM": 70, "courseControls": 20}, {"name": "Herren bis 10", "declaredStarters": 5, "results": [{"name": "Hartberger Peter", "club": "FUN-OL NÖ", "timeText": "10:55", "sourceBib": "662", "sourceNat": "AUT", "rank": 1, "timeS": 655, "status": "ok"}, {"name": "Kaltenbacher Tobias", "club": "HSV OL Wiener Neustadt", "timeText": "13:33", "sourceBib": "191", "sourceNat": "AUT", "rank": 2, "timeS": 813, "status": "ok"}, {"name": "Imriska Albert", "club": "Naturfreunde Wien", "timeText": "15:18", "sourceBib": "539", "sourceNat": "AUT", "rank": 3, "timeS": 918, "status": "ok"}, {"name": "Binder Lorenz", "club": "SU Klagenfurt", "timeText": "17:35", "sourceBib": "163", "sourceNat": "AUT", "rank": 4, "timeS": 1055, "status": "ok"}, {"name": "Haider Severin", "club": "WAT-OL", "timeText": "35:25", "sourceBib": "634", "sourceNat": "AUT", "rank": 5, "timeS": 2125, "status": "ok"}], "courseLengthM": 1200, "courseClimbM": 15, "courseControls": 13}, {"name": "Herren bis 12", "declaredStarters": 19, "results": [{"name": "Kaltenbacher David", "club": "HSV OL Wiener Neustadt", "timeText": "8:47", "sourceBib": "190", "sourceNat": "AUT", "rank": 1, "timeS": 527, "status": "ok"}, {"name": "Fuchs Michael", "club": "FUN-OL NÖ", "timeText": "9:32", "sourceBib": "660", "sourceNat": "AUT", "rank": 2, "timeS": 572, "status": "ok"}, {"name": "Zangerle David", "club": "Orienteering Innsbruck Imst", "timeText": "9:42", "sourceBib": "483", "sourceNat": "Imst AUT", "rank": 3, "timeS": 582, "status": "ok"}, {"name": "Reindl Leo", "club": "SU Klagenfurt", "timeText": "10:46", "sourceBib": "178", "sourceNat": "AUT", "rank": 4, "timeS": 646, "status": "ok"}, {"name": "Borsitzky Felix", "club": "HSV OL Wiener Neustadt", "timeText": "10:49", "sourceBib": "193", "sourceNat": "AUT", "rank": 5, "timeS": 649, "status": "ok"}, {"name": "Imriska Adam", "club": "Naturfreunde Wien", "timeText": "11:47", "sourceBib": "538", "sourceNat": "AUT", "rank": 6, "timeS": 707, "status": "ok"}, {"name": "Rothauer Tim", "club": "ASKÖ Henndorf Orienteering", "timeText": "13:11", "sourceBib": "308", "sourceNat": "AUT", "rank": 7, "timeS": 791, "status": "ok"}, {"name": "Schnepf Timo", "club": "OC Fürstenfeld", "timeText": "13:49", "sourceBib": "409", "sourceNat": "AUT", "rank": 8, "timeS": 829, "status": "ok"}, {"name": "Stanglechner Samuel", "club": "Orienteering Innsbruck Imst", "timeText": "15:38", "sourceBib": "470", "sourceNat": "Imst AUT", "rank": 9, "timeS": 938, "status": "ok"}, {"name": "Brawisch Ludwig", "club": "HSV Wals", "timeText": "15:49", "sourceBib": "318", "sourceNat": "AUT", "rank": 10, "timeS": 949, "status": "ok"}, {"name": "Hudax Jonah", "club": "OC Fürstenfeld", "timeText": "16:50", "sourceBib": "402", "sourceNat": "AUT", "rank": 11, "timeS": 1010, "status": "ok"}, {"name": "Jungmann Jakob", "club": "Orienteering Innsbruck Imst", "timeText": "19:26", "sourceBib": "452", "sourceNat": "Imst AUT", "rank": 12, "timeS": 1166, "status": "ok"}, {"name": "Kofler Jonas", "club": "HSV OL Villach", "timeText": "26:27", "sourceBib": "137", "sourceNat": "AUT", "rank": 13, "timeS": 1587, "status": "ok"}, {"name": "Haider Kilian", "club": "WAT-OL", "timeText": "31:23", "sourceBib": "633", "sourceNat": "AUT", "rank": 14, "timeS": 1883, "status": "ok"}, {"name": "Springer Jonas", "club": "OLCU Viktring", "timeText": "35:32", "sourceBib": "156", "sourceNat": "AUT", "rank": 15, "timeS": 2132, "status": "ok"}, {"name": "Maiorenko Oleksandr", "club": "Naturfreunde Wien", "timeText": "57:29", "sourceBib": "590", "sourceNat": "AUT", "rank": 16, "timeS": 3449, "status": "ok"}, {"name": "Hites Gergö", "club": "OLC Graz", "timeText": "Fehlst", "sourceBib": "357", "sourceNat": "AUT", "status": "mp"}, {"name": "Reindl Ben", "club": "SU Klagenfurt", "timeText": "Fehlst", "sourceBib": "177", "sourceNat": "AUT", "status": "mp"}, {"name": "Drizo Nikolai", "club": "Naturfreunde Wien", "timeText": "N Ang", "sourceBib": "588", "sourceNat": "AUT", "status": "dns"}], "courseLengthM": 1500, "courseClimbM": 15, "courseControls": 15}, {"name": "Herren bis 14", "declaredStarters": 15, "results": [{"name": "Grissemann Moritz", "club": "Orienteering Innsbruck Imst", "timeText": "9:24", "sourceBib": "447", "sourceNat": "Imst AUT", "rank": 1, "timeS": 564, "status": "ok"}, {"name": "Urbanek Lauri", "club": "Naturfreunde Wien", "timeText": "10:24", "sourceBib": "518", "sourceNat": "AUT", "rank": 2, "timeS": 624, "status": "ok"}, {"name": "Schmalhardt Matthias", "club": "OC Fürstenfeld", "timeText": "10:57", "sourceBib": "413", "sourceNat": "AUT", "rank": 3, "timeS": 657, "status": "ok"}, {"name": "Gstir Julius", "club": "Orienteering Innsbruck Imst", "timeText": "11:16", "sourceBib": "450", "sourceNat": "Imst AUT", "rank": 4, "timeS": 676, "status": "ok"}, {"name": "Kaiser Vincent", "club": "Naturfreunde Kitzbühel", "timeText": "11:45", "sourceBib": "506", "sourceNat": "AUT", "rank": 5, "timeS": 705, "status": "ok"}, {"name": "Hinterplattner Oskar", "club": "MTV Hernals", "timeText": "12:25", "sourceBib": "510", "sourceNat": "AUT", "rank": 6, "timeS": 745, "status": "ok"}, {"name": "Konrad Laurenz", "club": "OC Fürstenfeld", "timeText": "12:28", "sourceBib": "415", "sourceNat": "AUT", "rank": 7, "timeS": 748, "status": "ok"}, {"name": "Mangler Emil", "club": "WAT-OL", "timeText": "13:17", "sourceBib": "620", "sourceNat": "AUT", "rank": 8, "timeS": 797, "status": "ok"}, {"name": "Gollinger Paul", "club": "OC Fürstenfeld", "timeText": "13:40", "sourceBib": "414", "sourceNat": "AUT", "rank": 9, "timeS": 820, "status": "ok"}, {"name": "Renner Axel", "club": "OLC Graz", "timeText": "13:57", "sourceBib": "361", "sourceNat": "AUT", "rank": 10, "timeS": 837, "status": "ok"}, {"name": "Thurner Jonas", "club": "Orienteering Innsbruck Imst", "timeText": "13:59", "sourceBib": "477", "sourceNat": "Imst AUT", "rank": 11, "timeS": 839, "status": "ok"}, {"name": "Ochenbauer Jonas", "club": "HSV OL Wiener Neustadt", "timeText": "14:14", "sourceBib": "204", "sourceNat": "AUT", "rank": 12, "timeS": 854, "status": "ok"}, {"name": "Meizer Jannik", "club": "SU Klagenfurt", "timeText": "16:10", "sourceBib": "171", "sourceNat": "AUT", "rank": 13, "timeS": 970, "status": "ok"}, {"name": "Fischerleitner Lorenz", "club": "HSV Ried", "timeText": "20:29", "sourceBib": "247", "sourceNat": "AUT", "rank": 14, "timeS": 1229, "status": "ok"}, {"name": "Kofler Elias", "club": "HSV OL Villach", "timeText": "22:51", "sourceBib": "136", "sourceNat": "AUT", "rank": 15, "timeS": 1371, "status": "ok"}], "courseLengthM": 2100, "courseClimbM": 55, "courseControls": 16}, {"name": "Herren ab 15 bis 18", "declaredStarters": 5, "results": [{"name": "Lorenz Konrad", "club": "Orienteering Innsbruck Imst", "timeText": "10:54", "sourceBib": "453", "sourceNat": "Imst AUT", "rank": 1, "timeS": 654, "status": "ok"}, {"name": "Madl Leo", "club": "Orienteering Innsbruck Imst", "timeText": "11:37", "sourceBib": "491", "sourceNat": "Imst AUT", "rank": 2, "timeS": 697, "status": "ok"}, {"name": "Schöpf Lukas", "club": "Orienteering Innsbruck Imst", "timeText": "11:58", "sourceBib": "469", "sourceNat": "Imst AUT", "rank": 3, "timeS": 718, "status": "ok"}, {"name": "Oberkofler Jakob", "club": "OC Fürstenfeld", "timeText": "14:40", "sourceBib": "427", "sourceNat": "AUT", "rank": 4, "timeS": 880, "status": "ok"}, {"name": "Grüner Noah", "club": "Orienteering Innsbruck Imst", "timeText": "15:32", "sourceBib": "448", "sourceNat": "Imst AUT", "rank": 5, "timeS": 932, "status": "ok"}], "courseLengthM": 2000, "courseClimbM": 40, "courseControls": 16}, {"name": "Herren ab 21 Lang", "declaredStarters": 7, "results": [{"name": "Lapornik Dominik", "club": "HSV Großmittel", "timeText": "13:28", "sourceBib": "180", "sourceNat": "AUT", "rank": 1, "timeS": 808, "status": "ok"}, {"name": "Braun Emanuel jun.", "club": "HSV OL Wiener Neustadt", "timeText": "13:31", "sourceBib": "197", "sourceNat": "AUT", "rank": 2, "timeS": 811, "status": "ok"}, {"name": "Lindorfer Thomas", "club": "OLC Graz", "timeText": "15:05", "sourceBib": "366", "sourceNat": "AUT", "rank": 3, "timeS": 905, "status": "ok"}, {"name": "Traint Stefan", "club": "HSV OL Wiener Neustadt", "timeText": "15:07", "sourceBib": "213", "sourceNat": "AUT", "rank": 4, "timeS": 907, "status": "ok"}, {"name": "Obermüller Thomas", "club": "Naturfreunde Linz", "timeText": "15:09", "sourceBib": "263", "sourceNat": "AUT", "rank": 5, "timeS": 909, "status": "ok"}, {"name": "Falk Stefan", "club": "Naturfreunde Linz", "timeText": "21:16", "sourceBib": "270", "sourceNat": "AUT", "rank": 6, "timeS": 1276, "status": "ok"}, {"name": "Kainzbauer Peter", "club": "WAT-OL", "timeText": "22:26", "sourceBib": "617", "sourceNat": "AUT", "rank": 7, "timeS": 1346, "status": "ok"}], "courseLengthM": 3000, "courseClimbM": 95, "courseControls": 16}, {"name": "Herren ab 21 Kurz", "declaredStarters": 11, "results": [{"name": "Santaella Miguel Angel", "club": "Maz SU Schöckl Orienteering", "timeText": "13:52", "sourceBib": "391", "sourceNat": "AUT", "rank": 1, "timeS": 832, "status": "ok"}, {"name": "Ebster Peter", "club": "ASKÖ Henndorf Orienteering", "timeText": "14:46", "sourceBib": "311", "sourceNat": "AUT", "rank": 2, "timeS": 886, "status": "ok"}, {"name": "Eschlböck Jakob", "club": "Naturfreunde Linz", "timeText": "14:48", "sourceBib": "269", "sourceNat": "AUT", "rank": 3, "timeS": 888, "status": "ok"}, {"name": "Benkovic Fabian", "club": "Orienteering Innsbruck Imst", "timeText": "15:21", "sourceBib": "441", "sourceNat": "Imst AUT", "rank": 4, "timeS": 921, "status": "ok"}, {"name": "Schuh Roman", "club": "Orienteering Klosterneuburg", "timeText": "15:49", "sourceBib": "236", "sourceNat": "AUT", "rank": 5, "timeS": 949, "status": "ok"}, {"name": "Vogl Roland", "club": "ASKÖ Henndorf Orienteering", "timeText": "16:28", "sourceBib": "277", "sourceNat": "AUT", "rank": 6, "timeS": 988, "status": "ok"}, {"name": "Koiser Bernhard", "club": "HSV OL Wiener Neustadt", "timeText": "16:39", "sourceBib": "200", "sourceNat": "AUT", "rank": 7, "timeS": 999, "status": "ok"}, {"name": "Deubel Dirk", "club": "Naturfreunde Wien", "timeText": "17:22", "sourceBib": "578", "sourceNat": "AUT", "rank": 8, "timeS": 1042, "status": "ok"}, {"name": "Immervoll Christopher", "club": "SU Schöckl Orienteering", "timeText": "20:44", "sourceBib": "377", "sourceNat": "AUT", "rank": 9, "timeS": 1244, "status": "ok"}, {"name": "Kaminger William", "club": "Orienteering Klosterneuburg", "timeText": "20:56", "sourceBib": "220", "sourceNat": "AUT", "rank": 10, "timeS": 1256, "status": "ok"}, {"name": "Witting Rainer", "club": "Orienteering Innsbruck Imst", "timeText": "Fehlst", "sourceBib": "482", "sourceNat": "Imst AUT", "status": "mp"}], "courseLengthM": 2600, "courseClimbM": 75, "courseControls": 18}, {"name": "Herren ab 35", "declaredStarters": 3, "results": [{"name": "Euler-Rolle Nikolaus", "club": "Naturfreunde Wien", "timeText": "14:34", "sourceBib": "528", "sourceNat": "AUT", "rank": 1, "timeS": 874, "status": "ok"}, {"name": "Koppert Axel", "club": "OLC Graz", "timeText": "16:11", "sourceBib": "354", "sourceNat": "AUT", "rank": 2, "timeS": 971, "status": "ok"}, {"name": "Faccinelli Martin", "club": "SU Schöckl Orienteering", "timeText": "Fehlst", "sourceBib": "379", "sourceNat": "AUT", "status": "mp"}], "courseLengthM": 3000, "courseClimbM": 95, "courseControls": 16}, {"name": "Herren ab 40", "declaredStarters": 8, "results": [{"name": "Plohn Markus", "club": "HSV OL Wiener Neustadt", "timeText": "13:13", "sourceBib": "208", "sourceNat": "AUT", "rank": 1, "timeS": 793, "status": "ok"}, {"name": "Radon Thomas", "club": "Naturfreunde Wien", "timeText": "15:41", "sourceBib": "580", "sourceNat": "AUT", "rank": 2, "timeS": 941, "status": "ok"}, {"name": "Hudax Thomas", "club": "OC Fürstenfeld", "timeText": "15:44", "sourceBib": "401", "sourceNat": "AUT", "rank": 3, "timeS": 944, "status": "ok"}, {"name": "König Markus", "club": "ASKÖ Henndorf Orienteering", "timeText": "17:15", "sourceBib": "288", "sourceNat": "AUT", "rank": 4, "timeS": 1035, "status": "ok"}, {"name": "Imriska Samuel", "club": "Naturfreunde Wien", "timeText": "17:47", "sourceBib": "534", "sourceNat": "AUT", "rank": 5, "timeS": 1067, "status": "ok"}, {"name": "Melkes Zoltan", "club": "OL Kufstein", "timeText": "17:55", "sourceBib": "645", "sourceNat": "AUT", "rank": 6, "timeS": 1075, "status": "ok"}, {"name": "Neuhold Thomas", "club": "Orienteering Klosterneuburg", "timeText": "18:05", "sourceBib": "217", "sourceNat": "AUT", "rank": 7, "timeS": 1085, "status": "ok"}, {"name": "Meizer Felix", "club": "SU Klagenfurt", "timeText": "18:42", "sourceBib": "174", "sourceNat": "AUT", "rank": 8, "timeS": 1122, "status": "ok"}], "courseLengthM": 3000, "courseClimbM": 95, "courseControls": 16}, {"name": "Herren ab 45", "declaredStarters": 11, "results": [{"name": "Kaltenbacher Pierre", "club": "HSV OL Wiener Neustadt", "timeText": "11:45", "sourceBib": "189", "sourceNat": "AUT", "rank": 1, "timeS": 705, "status": "ok"}, {"name": "Mohn Christian", "club": "Leibnitzer AC OLG", "timeText": "11:59", "sourceBib": "339", "sourceNat": "AUT", "rank": 2, "timeS": 719, "status": "ok"}, {"name": "Egger Jürgen", "club": "Leibnitzer AC OLG", "timeText": "12:35", "sourceBib": "335", "sourceNat": "AUT", "rank": 3, "timeS": 755, "status": "ok"}, {"name": "Helminger Norbert", "club": "HSV Wals", "timeText": "12:37", "sourceBib": "320", "sourceNat": "AUT", "rank": 4, "timeS": 757, "status": "ok"}, {"name": "Haider Philipp", "club": "WAT-OL", "timeText": "12:40", "sourceBib": "615", "sourceNat": "AUT", "rank": 5, "timeS": 760, "status": "ok"}, {"name": "Venhauer Bernhard", "club": "OLCU Viktring", "timeText": "14:11", "sourceBib": "153", "sourceNat": "AUT", "rank": 6, "timeS": 851, "status": "ok"}, {"name": "Veitsberger Martin", "club": "OLT Transdanubien", "timeText": "14:17", "sourceBib": "606", "sourceNat": "AUT", "rank": 7, "timeS": 857, "status": "ok"}, {"name": "Wenzel Hannes", "club": "OLCU Viktring", "timeText": "14:30", "sourceBib": "157", "sourceNat": "AUT", "rank": 8, "timeS": 870, "status": "ok"}, {"name": "Deixler Norbert", "club": "HSV Pinkafeld", "timeText": "15:11", "sourceBib": "119", "sourceNat": "AUT", "rank": 9, "timeS": 911, "status": "ok"}, {"name": "Kolar Hannes", "club": "Naturfreunde Wien", "timeText": "16:28", "sourceBib": "530", "sourceNat": "AUT", "rank": 10, "timeS": 988, "status": "ok"}, {"name": "Marksteiner Martin", "club": "WAT-OL", "timeText": "16:34", "sourceBib": "626", "sourceNat": "AUT", "rank": 11, "timeS": 994, "status": "ok"}], "courseLengthM": 2800, "courseClimbM": 90, "courseControls": 20}, {"name": "Herren ab 50", "declaredStarters": 23, "results": [{"name": "Waldhäusl Wolfgang", "club": "Naturfreunde Wien", "timeText": "12:28", "sourceBib": "514", "sourceNat": "AUT", "rank": 1, "timeS": 748, "status": "ok"}, {"name": "Pölzl Andreas", "club": "Leibnitzer AC OLG", "timeText": "12:35", "sourceBib": "330", "sourceNat": "AUT", "rank": 2, "timeS": 755, "status": "ok"}, {"name": "Renner Wilfried", "club": "OLC Graz", "timeText": "13:49", "sourceBib": "360", "sourceNat": "AUT", "rank": 3, "timeS": 829, "status": "ok"}, {"name": "Bogensperger Martin", "club": "ASKÖ Henndorf Orienteering", "timeText": "13:51", "sourceBib": "283", "sourceNat": "AUT", "rank": 4, "timeS": 831, "status": "ok"}, {"name": "Helminger Franz", "club": "HSV Wals", "timeText": "13:53", "sourceBib": "317", "sourceNat": "AUT", "rank": 5, "timeS": 833, "status": "ok"}, {"name": "Huss Arno", "club": "SU Klagenfurt", "timeText": "14:24", "sourceBib": "159", "sourceNat": "AUT", "rank": 6, "timeS": 864, "status": "ok"}, {"name": "Wittberger Georg", "club": "HSV OL Wiener Neustadt", "timeText": "14:26", "sourceBib": "214", "sourceNat": "AUT", "rank": 7, "timeS": 866, "status": "ok"}, {"name": "Kastner-Jirka Boris", "club": "Naturfreunde Wien", "timeText": "14:36", "sourceBib": "565", "sourceNat": "AUT", "rank": 8, "timeS": 876, "status": "ok"}, {"name": "Aigmüller Thomas", "club": "SU Schöckl Orienteering", "timeText": "14:54", "sourceBib": "385", "sourceNat": "AUT", "rank": 9, "timeS": 894, "status": "ok"}, {"name": "Fischerleitner Peter", "club": "HSV Ried", "timeText": "15:28", "sourceBib": "245", "sourceNat": "AUT", "rank": 10, "timeS": 928, "status": "ok"}, {"name": "Kroupa Günther", "club": "Naturfreunde Wien", "timeText": "15:58", "sourceBib": "536", "sourceNat": "AUT", "rank": 11, "timeS": 958, "status": "ok"}, {"name": "Lechner Hannes", "club": "HSV Wals", "timeText": "16:04", "sourceBib": "321", "sourceNat": "AUT", "rank": 12, "timeS": 964, "status": "ok"}, {"name": "Borsitzky Hans", "club": "HSV OL Wiener Neustadt", "timeText": "16:08", "sourceBib": "194", "sourceNat": "AUT", "rank": 13, "timeS": 968, "status": "ok"}, {"name": "Poell Matthias", "club": "OLC Wienerwald", "timeText": "17:10", "sourceBib": "600", "sourceNat": "AUT", "rank": 14, "timeS": 1030, "status": "ok"}, {"name": "Dobler Georg", "club": "MTV Hernals", "timeText": "17:53", "sourceBib": "512", "sourceNat": "AUT", "rank": 15, "timeS": 1073, "status": "ok"}, {"name": "Gindu-Ferrari Wolfgang", "club": "Orienteering Innsbruck Imst", "timeText": "19:04", "sourceBib": "446", "sourceNat": "Imst AUT", "rank": 16, "timeS": 1144, "status": "ok"}, {"name": "Greiner Markus", "club": "SU Schöckl Orienteering", "timeText": "19:06", "sourceBib": "381", "sourceNat": "AUT", "rank": 17, "timeS": 1146, "status": "ok"}, {"name": "Leopoldseder Stefan", "club": "WAT-OL", "timeText": "19:24", "sourceBib": "628", "sourceNat": "AUT", "rank": 18, "timeS": 1164, "status": "ok"}, {"name": "Fink Carsten", "club": "SU Schöckl Orienteering", "timeText": "20:03", "sourceBib": "389", "sourceNat": "AUT", "rank": 19, "timeS": 1203, "status": "ok"}, {"name": "Kalcher Robert", "club": "HSV Pinkafeld", "timeText": "20:29", "sourceBib": "111", "sourceNat": "AUT", "rank": 20, "timeS": 1229, "status": "ok"}, {"name": "Kühr Gottfried", "club": "Naturfreunde Villach - Oriente", "timeText": "23:12", "sourceBib": "142", "sourceNat": "- Oriente AUT", "rank": 21, "timeS": 1392, "status": "ok"}, {"name": "Fuchs Martin", "club": "FUN-OL NÖ", "timeText": "N Ang", "sourceBib": "659", "sourceNat": "AUT", "status": "dns"}, {"name": "Mark Herbert", "club": "Orienteering Innsbruck Imst", "timeText": "N Ang", "sourceBib": "456", "sourceNat": "Imst AUT", "status": "dns"}], "courseLengthM": 2800, "courseClimbM": 65, "courseControls": 18}, {"name": "Herren ab 55", "declaredStarters": 24, "results": [{"name": "Gassner Ferri", "club": "Naturfreunde Wien", "timeText": "13:52", "sourceBib": "567", "sourceNat": "AUT", "rank": 1, "timeS": 832, "status": "ok"}, {"name": "Braun Emanuel", "club": "HSV OL Wiener Neustadt", "timeText": "15:15", "sourceBib": "196", "sourceNat": "AUT", "rank": 2, "timeS": 915, "status": "ok"}, {"name": "Hlosta Thomas", "club": "Naturfreunde Wien", "timeText": "15:34", "sourceBib": "525", "sourceNat": "AUT", "rank": 3, "timeS": 934, "status": "ok"}, {"name": "Täuber Thomas", "club": "OLT Transdanubien", "timeText": "15:35", "sourceBib": "609", "sourceNat": "AUT", "rank": 4, "timeS": 935, "status": "ok"}, {"name": "Hofstätter Felix", "club": "Naturfreunde Wien", "timeText": "15:42", "sourceBib": "571", "sourceNat": "AUT", "rank": 5, "timeS": 942, "status": "ok"}, {"name": "Reisenberger Roland", "club": "Orienteering Klosterneuburg", "timeText": "15:54", "sourceBib": "228", "sourceNat": "AUT", "rank": 6, "timeS": 954, "status": "ok"}, {"name": "Biel Axel", "club": "Naturfreunde Wien", "timeText": "15:57", "sourceBib": "559", "sourceNat": "AUT", "rank": 7, "timeS": 957, "status": "ok"}, {"name": "Gusel Franz", "club": "HSV Spittal / Drau", "timeText": "16:02", "sourceBib": "132", "sourceNat": "AUT", "rank": 8, "timeS": 962, "status": "ok"}, {"name": "Tiefenböck Wilhelm", "club": "Naturfreunde Wien", "timeText": "16:19", "sourceBib": "547", "sourceNat": "AUT", "rank": 9, "timeS": 979, "status": "ok"}, {"name": "Göschl Erich", "club": "OLC Wienerwald", "timeText": "16:34", "sourceBib": "596", "sourceNat": "AUT", "rank": 10, "timeS": 994, "status": "ok"}, {"name": "Ebster Sen. Peter", "club": "ASKÖ Henndorf Orienteering", "timeText": "16:49", "sourceBib": "304", "sourceNat": "AUT", "rank": 11, "timeS": 1009, "status": "ok"}, {"name": "Lerchegger Helmut", "club": "Leibnitzer AC OLG", "timeText": "17:12", "sourceBib": "338", "sourceNat": "AUT", "rank": 12, "timeS": 1032, "status": "ok"}, {"name": "Grill Michael", "club": "Naturfreunde Wien", "timeText": "17:19", "sourceBib": "522", "sourceNat": "AUT", "rank": 13, "timeS": 1039, "status": "ok"}, {"name": "Zöbl Gottfried", "club": "HSV Ried", "timeText": "17:33", "sourceBib": "254", "sourceNat": "AUT", "rank": 14, "timeS": 1053, "status": "ok"}, {"name": "Kuttner Michael", "club": "HSV Absam OL", "timeText": "17:42", "sourceBib": "436", "sourceNat": "AUT", "rank": 15, "timeS": 1062, "status": "ok"}, {"name": "Brabek Walter", "club": "OC Fürstenfeld", "timeText": "19:39", "sourceBib": "423", "sourceNat": "AUT", "rank": 16, "timeS": 1179, "status": "ok"}, {"name": "Eschlböck Rainer", "club": "Naturfreunde Linz", "timeText": "20:37", "sourceBib": "259", "sourceNat": "AUT", "rank": 17, "timeS": 1237, "status": "ok"}, {"name": "Sterba Markus", "club": "Orienteering Klosterneuburg", "timeText": "22:01", "sourceBib": "237", "sourceNat": "AUT", "rank": 18, "timeS": 1321, "status": "ok"}, {"name": "Gruber Rudolf", "club": "Naturfreunde Linz", "timeText": "23:37", "sourceBib": "273", "sourceNat": "AUT", "rank": 19, "timeS": 1417, "status": "ok"}, {"name": "Gojo Josef", "club": "SSV Dornbirn Schoren", "timeText": "32:03", "sourceBib": "101", "sourceNat": "AUT", "rank": 20, "timeS": 1923, "status": "ok"}, {"name": "Scheikl Gottfried", "club": "OC Fürstenfeld", "timeText": "Fehlst", "sourceBib": "404", "sourceNat": "AUT", "status": "mp"}, {"name": "Adenstedt Nikolaus", "club": "Orienteering Klosterneuburg", "timeText": "Fehlst", "sourceBib": "227", "sourceNat": "AUT", "status": "mp"}, {"name": "Lipphart-Kirchmeir Harald", "club": "HSV OL Wiener Neustadt", "timeText": "N Ang", "sourceBib": "202", "sourceNat": "AUT", "status": "dns"}, {"name": "Stockmayer Michael", "club": "HSV OL Wiener Neustadt", "timeText": "N Ang", "sourceBib": "212", "sourceNat": "AUT", "status": "dns"}], "courseLengthM": 2800, "courseClimbM": 65, "courseControls": 18}, {"name": "Herren ab 60", "declaredStarters": 17, "results": [{"name": "Opetnik Siegfried", "club": "HSV Spittal / Drau", "timeText": "13:54", "sourceBib": "133", "sourceNat": "AUT", "rank": 1, "timeS": 834, "status": "ok"}, {"name": "Kradischnig Wolfgang", "club": "Naturfreunde Linz", "timeText": "14:03", "sourceBib": "266", "sourceNat": "AUT", "rank": 2, "timeS": 843, "status": "ok"}, {"name": "Zapletal Josef", "club": "Naturfreunde Wien", "timeText": "14:28", "sourceBib": "535", "sourceNat": "AUT", "rank": 3, "timeS": 868, "status": "ok"}, {"name": "Proske Herwig", "club": "OC Fürstenfeld", "timeText": "15:10", "sourceBib": "394", "sourceNat": "AUT", "rank": 4, "timeS": 910, "status": "ok"}, {"name": "Lang Karl", "club": "HSV Pinkafeld", "timeText": "16:25", "sourceBib": "102", "sourceNat": "AUT", "rank": 5, "timeS": 985, "status": "ok"}, {"name": "Billroth Georg", "club": "Orienteering Klosterneuburg", "timeText": "16:28", "sourceBib": "235", "sourceNat": "AUT", "rank": 6, "timeS": 988, "status": "ok"}, {"name": "Pregartner Georg", "club": "SKV OLG Deutsch Kaltenbrunn", "timeText": "16:56", "sourceBib": "128", "sourceNat": "Kaltenbrunn AUT", "rank": 7, "timeS": 1016, "status": "ok"}, {"name": "Polster Josef", "club": "HSV Spittal / Drau", "timeText": "17:04", "sourceBib": "134", "sourceNat": "AUT", "rank": 8, "timeS": 1024, "status": "ok"}, {"name": "Kradischnig Günter", "club": "OLC Graz", "timeText": "18:22", "sourceBib": "349", "sourceNat": "AUT", "rank": 9, "timeS": 1102, "status": "ok"}, {"name": "Pühringer Dieter", "club": "Naturfreunde Linz", "timeText": "19:06", "sourceBib": "272", "sourceNat": "AUT", "rank": 10, "timeS": 1146, "status": "ok"}, {"name": "Tanner Helmut", "club": "OLCU Viktring", "timeText": "21:34", "sourceBib": "158", "sourceNat": "AUT", "rank": 11, "timeS": 1294, "status": "ok"}, {"name": "Binder Josef", "club": "LZ OMAHA", "timeText": "24:42", "sourceBib": "122", "sourceNat": "AUT", "rank": 12, "timeS": 1482, "status": "ok"}, {"name": "Wolfram Arnulf", "club": "WAT-OL", "timeText": "25:41", "sourceBib": "612", "sourceNat": "AUT", "rank": 13, "timeS": 1541, "status": "ok"}, {"name": "Bruckner Franz", "club": "HSV Pinkafeld", "timeText": "29:53", "sourceBib": "104", "sourceNat": "AUT", "rank": 14, "timeS": 1793, "status": "ok"}, {"name": "Elstner Florian", "club": "ASKÖ Henndorf Orienteering", "timeText": "Fehlst", "sourceBib": "284", "sourceNat": "AUT", "status": "mp"}, {"name": "Mayer Horst", "club": "SSV Hallein-Neualm", "timeText": "Fehlst", "sourceBib": "326", "sourceNat": "AUT", "status": "mp"}, {"name": "Wiesinger Georg", "club": "Naturfreunde Wien", "timeText": "Fehlst", "sourceBib": "527", "sourceNat": "AUT", "status": "mp"}], "courseLengthM": 2500, "courseClimbM": 60, "courseControls": 15}, {"name": "Herren ab 65", "declaredStarters": 20, "results": [{"name": "Wechselberger Johannes", "club": "OL Kufstein", "timeText": "13:48", "sourceBib": "641", "sourceNat": "AUT", "rank": 1, "timeS": 828, "status": "ok"}, {"name": "Johansson Bernt", "club": "HSV Absam OL", "timeText": "15:24", "sourceBib": "431", "sourceNat": "AUT", "rank": 2, "timeS": 924, "status": "ok"}, {"name": "Friessnig Joachim", "club": "OC Fürstenfeld", "timeText": "15:32", "sourceBib": "405", "sourceNat": "AUT", "rank": 3, "timeS": 932, "status": "ok"}, {"name": "Purgathofer Werner", "club": "OLG Ströck Wien", "timeText": "16:04", "sourceBib": "602", "sourceNat": "AUT", "rank": 4, "timeS": 964, "status": "ok"}, {"name": "Grün Paul", "club": "OLG Ströck Wien", "timeText": "16:26", "sourceBib": "604", "sourceNat": "AUT", "rank": 5, "timeS": 986, "status": "ok"}, {"name": "Genevois Frederic", "club": "Naturfreunde Wien", "timeText": "16:41", "sourceBib": "545", "sourceNat": "AUT", "rank": 6, "timeS": 1001, "status": "ok"}, {"name": "Mayrhofer Gerald", "club": "SKV OLG Deutsch Kaltenbrunn", "timeText": "17:22", "sourceBib": "131", "sourceNat": "Kaltenbrunn AUT", "rank": 7, "timeS": 1042, "status": "ok"}, {"name": "Ivansson Jan", "club": "HSV Absam OL", "timeText": "18:27", "sourceBib": "433", "sourceNat": "AUT", "rank": 8, "timeS": 1107, "status": "ok"}, {"name": "Wimmer Josef", "club": "ASKÖ Henndorf Orienteering", "timeText": "19:11", "sourceBib": "281", "sourceNat": "AUT", "rank": 9, "timeS": 1151, "status": "ok"}, {"name": "Bosina Martin", "club": "Naturfreunde Wien", "timeText": "19:37", "sourceBib": "521", "sourceNat": "AUT", "rank": 10, "timeS": 1177, "status": "ok"}, {"name": "Werther Wolfgang", "club": "WATV", "timeText": "19:52", "sourceBib": "637", "sourceNat": "AUT", "rank": 11, "timeS": 1192, "status": "ok"}, {"name": "Mayer Johannes", "club": "OLC Wienerwald", "timeText": "19:55", "sourceBib": "597", "sourceNat": "AUT", "rank": 12, "timeS": 1195, "status": "ok"}, {"name": "Leonhardt Kristian", "club": "OC Fürstenfeld", "timeText": "20:09", "sourceBib": "398", "sourceNat": "AUT", "rank": 13, "timeS": 1209, "status": "ok"}, {"name": "Rogl Hartwig", "club": "Naturfreunde Seekirchen", "timeText": "20:53", "sourceBib": "324", "sourceNat": "AUT", "rank": 14, "timeS": 1253, "status": "ok"}, {"name": "Strobl Herbert", "club": "HSV Pinkafeld", "timeText": "24:13", "sourceBib": "106", "sourceNat": "AUT", "rank": 15, "timeS": 1453, "status": "ok"}, {"name": "Scheibenreif Johann", "club": "HSV Linz", "timeText": "24:39", "sourceBib": "244", "sourceNat": "AUT", "rank": 16, "timeS": 1479, "status": "ok"}, {"name": "Mages Franz", "club": "SSV Hallein-Neualm", "timeText": "24:44", "sourceBib": "325", "sourceNat": "AUT", "rank": 17, "timeS": 1484, "status": "ok"}, {"name": "Hackl Karl", "club": "ASKÖ Henndorf Orienteering", "timeText": "26:44", "sourceBib": "287", "sourceNat": "AUT", "rank": 18, "timeS": 1604, "status": "ok"}, {"name": "Auer Kurt", "club": "Naturfreunde Linz", "timeText": "28:30", "sourceBib": "262", "sourceNat": "AUT", "rank": 19, "timeS": 1710, "status": "ok"}, {"name": "Schnegg Peter", "club": "HSV Absam OL", "timeText": "Fehlst", "sourceBib": "435", "sourceNat": "AUT", "status": "mp"}], "courseLengthM": 2500, "courseClimbM": 60, "courseControls": 15}, {"name": "Herren ab 70", "declaredStarters": 14, "results": [{"name": "Ponweiser Franz", "club": "HSV OL Wiener Neustadt", "timeText": "11:41", "sourceBib": "210", "sourceNat": "AUT", "rank": 1, "timeS": 701, "status": "ok"}, {"name": "Schweifer Erwin", "club": "HSV OL Wiener Neustadt", "timeText": "12:38", "sourceBib": "211", "sourceNat": "AUT", "rank": 2, "timeS": 758, "status": "ok"}, {"name": "Melkes Antal", "club": "Orienteering Innsbruck Imst", "timeText": "14:26", "sourceBib": "458", "sourceNat": "Imst AUT", "rank": 3, "timeS": 866, "status": "ok"}, {"name": "Lukaseder Hubert", "club": "HSV Langenlebarn", "timeText": "14:54", "sourceBib": "187", "sourceNat": "AUT", "rank": 4, "timeS": 894, "status": "ok"}, {"name": "Pongratz Karl", "club": "HSV Pinkafeld", "timeText": "15:12", "sourceBib": "110", "sourceNat": "AUT", "rank": 5, "timeS": 912, "status": "ok"}, {"name": "Hechl Georg", "club": "Naturfreunde Kitzbühel", "timeText": "15:41", "sourceBib": "502", "sourceNat": "AUT", "rank": 6, "timeS": 941, "status": "ok"}, {"name": "Prommer Günther", "club": "Naturfreunde Villach - Oriente", "timeText": "15:45", "sourceBib": "146", "sourceNat": "- Oriente AUT", "rank": 7, "timeS": 945, "status": "ok"}, {"name": "Germ Wolfgang", "club": "Naturfreunde Villach - Oriente", "timeText": "16:06", "sourceBib": "139", "sourceNat": "- Oriente AUT", "rank": 8, "timeS": 966, "status": "ok"}, {"name": "Ziegerhofer Othmar", "club": "Naturfreunde Linz", "timeText": "16:45", "sourceBib": "267", "sourceNat": "AUT", "rank": 9, "timeS": 1005, "status": "ok"}, {"name": "Werner Richard", "club": "SSV Dornbirn Schoren", "timeText": "22:58", "sourceBib": "100", "sourceNat": "AUT", "rank": 10, "timeS": 1378, "status": "ok"}, {"name": "Müller Leo", "club": "ASKÖ Henndorf Orienteering", "timeText": "1:15:32", "sourceBib": "279", "sourceNat": "AUT", "rank": 11, "timeS": 4532, "status": "ok"}, {"name": "Hartinger Sepp", "club": "Leibnitzer AC OLG", "timeText": "Fehlst", "sourceBib": "333", "sourceNat": "AUT", "status": "mp"}, {"name": "Avramenko Oleksandr", "club": "Orienteering Klosterneuburg", "timeText": "Fehlst", "sourceBib": "229", "sourceNat": "AUT", "status": "mp"}, {"name": "Hartinger Franz", "club": "Leibnitzer AC OLG", "timeText": "Aufg", "sourceBib": "331", "sourceNat": "AUT", "status": "dnf"}], "courseLengthM": 1700, "courseClimbM": 50, "courseControls": 12}, {"name": "Herren ab 75", "declaredStarters": 8, "results": [{"name": "Böhm Eduard", "club": "ASKÖ Henndorf Orienteering", "timeText": "12:50", "sourceBib": "290", "sourceNat": "AUT", "rank": 1, "timeS": 770, "status": "ok"}, {"name": "Tonka Leopold", "club": "HSV Wals", "timeText": "13:38", "sourceBib": "315", "sourceNat": "AUT", "rank": 2, "timeS": 818, "status": "ok"}, {"name": "Burmann Werner", "club": "OLC Wienerwald", "timeText": "13:47", "sourceBib": "599", "sourceNat": "AUT", "rank": 3, "timeS": 827, "status": "ok"}, {"name": "Grabenhofer Wilhelm", "club": "LZ OMAHA", "timeText": "16:36", "sourceBib": "124", "sourceNat": "AUT", "rank": 4, "timeS": 996, "status": "ok"}, {"name": "Siegert Reinhard", "club": "WAT-OL", "timeText": "17:09", "sourceBib": "625", "sourceNat": "AUT", "rank": 5, "timeS": 1029, "status": "ok"}, {"name": "Schanz Ferdinand", "club": "Leibnitzer AC OLG", "timeText": "21:52", "sourceBib": "343", "sourceNat": "AUT", "rank": 6, "timeS": 1312, "status": "ok"}, {"name": "Krausmann Walter", "club": "HSV Ried", "timeText": "Fehlst", "sourceBib": "249", "sourceNat": "AUT", "status": "mp"}, {"name": "Maier Curt", "club": "ASKÖ OLC Ebenthal", "timeText": "N Ang", "sourceBib": "655", "sourceNat": "AUT", "status": "dns"}], "courseLengthM": 1700, "courseClimbM": 50, "courseControls": 12}, {"name": "Herren ab 80", "declaredStarters": 4, "results": [{"name": "Bonek Ernst", "club": "Naturfreunde Wien", "timeText": "12:47", "sourceBib": "532", "sourceNat": "AUT", "rank": 1, "timeS": 767, "status": "ok"}, {"name": "Venhauer Otto", "club": "OLCU Viktring", "timeText": "14:50", "sourceBib": "148", "sourceNat": "AUT", "rank": 2, "timeS": 890, "status": "ok"}, {"name": "Kochmann Günther", "club": "WAT-OL", "timeText": "19:45", "sourceBib": "618", "sourceNat": "AUT", "rank": 3, "timeS": 1185, "status": "ok"}, {"name": "Knoflach Hermann", "club": "HSV Absam OL", "timeText": "23:06", "sourceBib": "439", "sourceNat": "AUT", "rank": 4, "timeS": 1386, "status": "ok"}], "courseLengthM": 1600, "courseClimbM": 40, "courseControls": 14}, {"name": "Herren Hobby", "declaredStarters": 8, "results": [{"name": "Hites Viktor", "club": "OLC Graz", "timeText": "11:38", "sourceBib": "356", "sourceNat": "AUT", "rank": 1, "timeS": 698, "status": "ok"}, {"name": "Berr Hans Jörg", "club": "Leibnitzer AC OLG", "timeText": "14:46", "sourceBib": "328", "sourceNat": "AUT", "rank": 2, "timeS": 886, "status": "ok"}, {"name": "Skern Tim", "club": "Naturfreunde Wien", "timeText": "15:34", "sourceBib": "533", "sourceNat": "AUT", "rank": 3, "timeS": 934, "status": "ok"}, {"name": "Bonek Peter", "club": "Naturfreunde Wien", "timeText": "16:31", "sourceBib": "556", "sourceNat": "AUT", "rank": 4, "timeS": 991, "status": "ok"}, {"name": "Paier Mario", "club": "WAT-OL", "timeText": "21:00", "sourceBib": "614", "sourceNat": "AUT", "rank": 5, "timeS": 1260, "status": "ok"}, {"name": "Masarovic Dominic", "club": "HSV Großmittel", "timeText": "22:16", "sourceBib": "186", "sourceNat": "AUT", "rank": 6, "timeS": 1336, "status": "ok"}, {"name": "Kainzbauer Josef", "club": "WAT-OL", "timeText": "31:56", "sourceBib": "616", "sourceNat": "AUT", "rank": 7, "timeS": 1916, "status": "ok"}, {"name": "Lueger Reinhold", "club": "SU Schöckl Orienteering", "timeText": "Fehlst", "sourceBib": "386", "sourceNat": "AUT", "status": "mp"}], "courseLengthM": 2000, "courseClimbM": 40, "courseControls": 16}, {"name": "Damen ab 21 Elite", "declaredStarters": 25, "results": [{"name": "Kastner Ylvi", "club": "Naturfreunde Wien", "timeText": "12:50", "sourceBib": "543", "sourceNat": "AUT", "rank": 1, "timeS": 770, "status": "ok"}, {"name": "Ramstein Laura", "club": "OLC Graz", "timeText": "12:58", "sourceBib": "351", "sourceNat": "AUT", "rank": 2, "timeS": 778, "status": "ok"}, {"name": "Gassner Jasmina", "club": "Naturfreunde Wien", "timeText": "12:58", "sourceBib": "573", "sourceNat": "AUT", "rank": 2, "timeS": 778, "status": "ok"}, {"name": "Polzer Carina", "club": "SU Klagenfurt", "timeText": "12:59", "sourceBib": "166", "sourceNat": "AUT", "rank": 4, "timeS": 779, "status": "ok"}, {"name": "Gröll Anna", "club": "OLC Graz", "timeText": "13:21", "sourceBib": "365", "sourceNat": "AUT", "rank": 5, "timeS": 801, "status": "ok"}, {"name": "Nilsson Simkovics", "club": "Anna OLC Wienerwald", "timeText": "13:23", "sourceBib": "595", "sourceNat": "AUT", "rank": 6, "timeS": 803, "status": "ok"}, {"name": "Tiefenböck Tina", "club": "Naturfreunde Wien", "timeText": "13:27", "sourceBib": "549", "sourceNat": "AUT", "rank": 7, "timeS": 807, "status": "ok"}, {"name": "Gassner Anika", "club": "Naturfreunde Wien", "timeText": "13:43", "sourceBib": "583", "sourceNat": "AUT", "rank": 8, "timeS": 823, "status": "ok"}, {"name": "Buchberger Lina", "club": "Naturfreunde Wien", "timeText": "14:33", "sourceBib": "542", "sourceNat": "AUT", "rank": 9, "timeS": 873, "status": "ok"}, {"name": "Ying Yau Chu Stephanie", "club": "ASKÖ Henndorf Orienteering", "timeText": "15:16", "sourceBib": "280", "sourceNat": "AUT", "rank": 10, "timeS": 916, "status": "ok"}, {"name": "Trummer Johanna", "club": "OLC Graz", "timeText": "15:18", "sourceBib": "358", "sourceNat": "AUT", "rank": 11, "timeS": 918, "status": "ok"}, {"name": "Berger Anni", "club": "Orienteering Klosterneuburg", "timeText": "15:18", "sourceBib": "234", "sourceNat": "AUT", "rank": 11, "timeS": 918, "status": "ok"}, {"name": "Kastner Maya", "club": "Naturfreunde Wien", "timeText": "15:24", "sourceBib": "574", "sourceNat": "AUT", "rank": 13, "timeS": 924, "status": "ok"}, {"name": "Erhart Antonia", "club": "OLC Graz", "timeText": "15:40", "sourceBib": "353", "sourceNat": "AUT", "rank": 14, "timeS": 940, "status": "ok"}, {"name": "Walch Martina", "club": "OLC Graz", "timeText": "15:56", "sourceBib": "359", "sourceNat": "AUT", "rank": 15, "timeS": 956, "status": "ok"}, {"name": "Lueger Anna", "club": "SU Schöckl Orienteering", "timeText": "16:02", "sourceBib": "375", "sourceNat": "AUT", "rank": 16, "timeS": 962, "status": "ok"}, {"name": "Trummer Rosa", "club": "OLC Graz", "timeText": "16:52", "sourceBib": "367", "sourceNat": "AUT", "rank": 17, "timeS": 1012, "status": "ok"}, {"name": "Mäkinen Elisa", "club": "ASKÖ Henndorf Orienteering", "timeText": "16:56", "sourceBib": "303", "sourceNat": "AUT", "rank": 18, "timeS": 1016, "status": "ok"}, {"name": "Bogensperger Nilla", "club": "ASKÖ Henndorf Orienteering", "timeText": "17:04", "sourceBib": "294", "sourceNat": "AUT", "rank": 19, "timeS": 1024, "status": "ok"}, {"name": "Gleirscher Nadine", "club": "HSV Absam OL", "timeText": "17:28", "sourceBib": "430", "sourceNat": "AUT", "rank": 20, "timeS": 1048, "status": "ok"}, {"name": "Döllgast Nina", "club": "ASKÖ Henndorf Orienteering", "timeText": "17:41", "sourceBib": "282", "sourceNat": "AUT", "rank": 21, "timeS": 1061, "status": "ok"}, {"name": "Sturm Anna", "club": "Orienteering Innsbruck Imst", "timeText": "19:24", "sourceBib": "473", "sourceNat": "Imst AUT", "rank": 22, "timeS": 1164, "status": "ok"}, {"name": "Seidl Alina", "club": "Naturfreunde Wien", "timeText": "20:59", "sourceBib": "546", "sourceNat": "AUT", "rank": 23, "timeS": 1259, "status": "ok"}, {"name": "Muschinska Amelia", "club": "Orienteering Innsbruck Imst", "timeText": "N Ang", "sourceBib": "459", "sourceNat": "Imst AUT", "status": "dns"}, {"name": "Tyner Zoë", "club": "HSV Absam OL", "timeText": "N Ang", "sourceBib": "429", "sourceNat": "AUT", "status": "dns"}], "courseLengthM": 3000, "courseClimbM": 100, "courseControls": 20}, {"name": "Damen bis 20 Elite", "declaredStarters": 3, "results": [{"name": "Aigmüller Flora", "club": "SU Schöckl Orienteering", "timeText": "12:56", "sourceBib": "370", "sourceNat": "AUT", "rank": 1, "timeS": 776, "status": "ok"}, {"name": "Winkler Hannah", "club": "SU Schöckl Orienteering", "timeText": "13:26", "sourceBib": "369", "sourceNat": "AUT", "rank": 2, "timeS": 806, "status": "ok"}, {"name": "Angermann Anna", "club": "SU Klagenfurt", "timeText": "15:29", "sourceBib": "167", "sourceNat": "AUT", "rank": 3, "timeS": 929, "status": "ok"}], "courseLengthM": 2600, "courseClimbM": 75, "courseControls": 18}, {"name": "Damen bis 18 Elite", "declaredStarters": 11, "results": [{"name": "Monsberger Theresa", "club": "SU Schöckl Orienteering", "timeText": "13:23", "sourceBib": "376", "sourceNat": "AUT", "rank": 1, "timeS": 803, "status": "ok"}, {"name": "Varga Marie", "club": "LZ OMAHA", "timeText": "13:38", "sourceBib": "125", "sourceNat": "AUT", "rank": 2, "timeS": 818, "status": "ok"}, {"name": "Perl Katharina", "club": "OC Fürstenfeld", "timeText": "13:40", "sourceBib": "406", "sourceNat": "AUT", "rank": 3, "timeS": 820, "status": "ok"}, {"name": "Aigmüller Camilla", "club": "SU Schöckl Orienteering", "timeText": "13:40", "sourceBib": "371", "sourceNat": "AUT", "rank": 3, "timeS": 820, "status": "ok"}, {"name": "Biel Corinna", "club": "Naturfreunde Wien", "timeText": "14:15", "sourceBib": "560", "sourceNat": "AUT", "rank": 5, "timeS": 855, "status": "ok"}, {"name": "Radon Livia", "club": "Naturfreunde Wien", "timeText": "15:01", "sourceBib": "581", "sourceNat": "AUT", "rank": 6, "timeS": 901, "status": "ok"}, {"name": "Venhauer Laura", "club": "OLCU Viktring", "timeText": "15:50", "sourceBib": "151", "sourceNat": "AUT", "rank": 7, "timeS": 950, "status": "ok"}, {"name": "Scheikl Helene", "club": "OC Fürstenfeld", "timeText": "16:57", "sourceBib": "403", "sourceNat": "AUT", "rank": 8, "timeS": 1017, "status": "ok"}, {"name": "Gaudernak Carina", "club": "OLT Transdanubien", "timeText": "19:39", "sourceBib": "610", "sourceNat": "AUT", "rank": 9, "timeS": 1179, "status": "ok"}, {"name": "Adenstedt Emily", "club": "Orienteering Klosterneuburg", "timeText": "20:36", "sourceBib": "222", "sourceNat": "AUT", "rank": 10, "timeS": 1236, "status": "ok"}, {"name": "Hufnagel Carolina", "club": "Naturfreunde Wien", "timeText": "24:14", "sourceBib": "564", "sourceNat": "AUT", "rank": 11, "timeS": 1454, "status": "ok"}], "courseLengthM": 2600, "courseClimbM": 75, "courseControls": 18}, {"name": "Damen bis 16 Elite", "declaredStarters": 10, "results": [{"name": "Asenbauer Sona", "club": "Naturfreunde Wien", "timeText": "10:52", "sourceBib": "563", "sourceNat": "AUT", "rank": 1, "timeS": 652, "status": "ok"}, {"name": "Friedl Eva", "club": "HSV Pinkafeld", "timeText": "10:58", "sourceBib": "114", "sourceNat": "AUT", "rank": 2, "timeS": 658, "status": "ok"}, {"name": "Asenbauer Mika", "club": "Naturfreunde Wien", "timeText": "11:12", "sourceBib": "562", "sourceNat": "AUT", "rank": 3, "timeS": 672, "status": "ok"}, {"name": "Piskorz Kiara-Sophie", "club": "WAT-OL", "timeText": "11:58", "sourceBib": "623", "sourceNat": "AUT", "rank": 4, "timeS": 718, "status": "ok"}, {"name": "Egger Lilli", "club": "Orienteering Innsbruck Imst", "timeText": "12:37", "sourceBib": "442", "sourceNat": "Imst AUT", "rank": 5, "timeS": 757, "status": "ok"}, {"name": "Hauser Maria", "club": "Naturfreunde Kitzbühel", "timeText": "13:04", "sourceBib": "497", "sourceNat": "AUT", "rank": 6, "timeS": 784, "status": "ok"}, {"name": "Helminger Katja", "club": "HSV Wals", "timeText": "13:40", "sourceBib": "316", "sourceNat": "AUT", "rank": 7, "timeS": 820, "status": "ok"}, {"name": "Paier Paula", "club": "WAT-OL", "timeText": "14:43", "sourceBib": "621", "sourceNat": "AUT", "rank": 8, "timeS": 883, "status": "ok"}, {"name": "Mohn Lilianne", "club": "Leibnitzer AC OLG", "timeText": "27:14", "sourceBib": "342", "sourceNat": "AUT", "rank": 9, "timeS": 1634, "status": "ok"}, {"name": "Brischnik Charlotte", "club": "SU Schöckl Orienteering", "timeText": "Fehlst", "sourceBib": "372", "sourceNat": "AUT", "status": "mp"}], "courseLengthM": 2200, "courseClimbM": 50, "courseControls": 17}, {"name": "Damen bis 10", "declaredStarters": 6, "results": [{"name": "Egger Marie", "club": "Leibnitzer AC OLG", "timeText": "9:41", "sourceBib": "336", "sourceNat": "AUT", "rank": 1, "timeS": 581, "status": "ok"}, {"name": "Meizer Lucia", "club": "SU Klagenfurt", "timeText": "12:50", "sourceBib": "172", "sourceNat": "AUT", "rank": 2, "timeS": 770, "status": "ok"}, {"name": "Leonhardt Jara", "club": "OC Fürstenfeld", "timeText": "13:34", "sourceBib": "948", "sourceNat": "AUT", "rank": 3, "timeS": 814, "status": "ok"}, {"name": "Binder Annika", "club": "SU Klagenfurt", "timeText": "21:09", "sourceBib": "162", "sourceNat": "AUT", "rank": 4, "timeS": 1269, "status": "ok"}, {"name": "Stricker Mia", "club": "Orienteering Innsbruck Imst", "timeText": "Fehlst", "sourceBib": "472", "sourceNat": "Imst AUT", "status": "mp"}, {"name": "Witting Ariella", "club": "Orienteering Innsbruck Imst", "timeText": "N Ang", "sourceBib": "479", "sourceNat": "Imst AUT", "status": "dns"}], "courseLengthM": 1200, "courseClimbM": 15, "courseControls": 13}, {"name": "Damen bis 12", "declaredStarters": 17, "results": [{"name": "Mair Sarah", "club": "Orienteering Innsbruck Imst", "timeText": "7:42", "sourceBib": "455", "sourceNat": "Imst AUT", "rank": 1, "timeS": 462, "status": "ok"}, {"name": "Skern Anna", "club": "Naturfreunde Wien", "timeText": "8:36", "sourceBib": "520", "sourceNat": "AUT", "rank": 2, "timeS": 516, "status": "ok"}, {"name": "Urbanek Annina", "club": "Naturfreunde Wien", "timeText": "9:47", "sourceBib": "517", "sourceNat": "AUT", "rank": 3, "timeS": 587, "status": "ok"}, {"name": "Schönberger Marion", "club": "ASKÖ Henndorf Orienteering", "timeText": "10:06", "sourceBib": "299", "sourceNat": "AUT", "rank": 4, "timeS": 606, "status": "ok"}, {"name": "Klöckl Mira", "club": "Orienteering Klosterneuburg", "timeText": "10:37", "sourceBib": "226", "sourceNat": "AUT", "rank": 5, "timeS": 637, "status": "ok"}, {"name": "Elenbaas Hanna", "club": "Orienteering Innsbruck Imst", "timeText": "11:43", "sourceBib": "443", "sourceNat": "Imst AUT", "rank": 6, "timeS": 703, "status": "ok"}, {"name": "Ofner Emilie", "club": "FUN-OL NÖ", "timeText": "12:08", "sourceBib": "663", "sourceNat": "AUT", "rank": 7, "timeS": 728, "status": "ok"}, {"name": "Melkes Zora", "club": "OL Kufstein", "timeText": "12:52", "sourceBib": "652", "sourceNat": "AUT", "rank": 8, "timeS": 772, "status": "ok"}, {"name": "Sturm Florentina", "club": "Orienteering Innsbruck Imst", "timeText": "14:38", "sourceBib": "474", "sourceNat": "Imst AUT", "rank": 9, "timeS": 878, "status": "ok"}, {"name": "Knoflach Katharina", "club": "Orienteering Innsbruck Imst", "timeText": "15:36", "sourceBib": "485", "sourceNat": "Imst AUT", "rank": 10, "timeS": 936, "status": "ok"}, {"name": "Rass Magdalena", "club": "Orienteering Innsbruck Imst", "timeText": "16:29", "sourceBib": "465", "sourceNat": "Imst AUT", "rank": 11, "timeS": 989, "status": "ok"}, {"name": "Hauser Anna", "club": "Naturfreunde Kitzbühel", "timeText": "17:57", "sourceBib": "496", "sourceNat": "AUT", "rank": 12, "timeS": 1077, "status": "ok"}, {"name": "Gattringer Mia", "club": "HSV Ried", "timeText": "18:57", "sourceBib": "251", "sourceNat": "AUT", "rank": 13, "timeS": 1137, "status": "ok"}, {"name": "Hauser Lisa", "club": "Naturfreunde Kitzbühel", "timeText": "19:06", "sourceBib": "495", "sourceNat": "AUT", "rank": 14, "timeS": 1146, "status": "ok"}, {"name": "Stricker Lea", "club": "Orienteering Innsbruck Imst", "timeText": "21:08", "sourceBib": "471", "sourceNat": "Imst AUT", "rank": 15, "timeS": 1268, "status": "ok"}, {"name": "Houdek Pia", "club": "OC Fürstenfeld", "timeText": "N Ang", "sourceBib": "418", "sourceNat": "AUT", "status": "dns"}, {"name": "Mitterer Sarah", "club": "ASKÖ Henndorf Orienteering", "timeText": "N Ang", "sourceBib": "302", "sourceNat": "AUT", "status": "dns"}], "courseLengthM": 1500, "courseClimbM": 15, "courseControls": 15}, {"name": "Damen bis 14", "declaredStarters": 20, "results": [{"name": "Gigler Viktoria", "club": "OC Fürstenfeld", "timeText": "11:17", "sourceBib": "416", "sourceNat": "AUT", "rank": 1, "timeS": 677, "status": "ok"}, {"name": "Mohn Jonna", "club": "Leibnitzer AC OLG", "timeText": "11:23", "sourceBib": "341", "sourceNat": "AUT", "rank": 2, "timeS": 683, "status": "ok"}, {"name": "Buschek Matilda", "club": "Naturfreunde Wien", "timeText": "12:12", "sourceBib": "569", "sourceNat": "AUT", "rank": 3, "timeS": 732, "status": "ok"}, {"name": "Machold Cleo", "club": "Naturfreunde Wien", "timeText": "12:24", "sourceBib": "576", "sourceNat": "AUT", "rank": 4, "timeS": 744, "status": "ok"}, {"name": "Grüner Pia", "club": "Orienteering Innsbruck Imst", "timeText": "12:51", "sourceBib": "449", "sourceNat": "Imst AUT", "rank": 5, "timeS": 771, "status": "ok"}, {"name": "Grangl Luisa", "club": "OC Fürstenfeld", "timeText": "12:53", "sourceBib": "417", "sourceNat": "AUT", "rank": 6, "timeS": 773, "status": "ok"}, {"name": "Fuchs Lena", "club": "FUN-OL NÖ", "timeText": "13:20", "sourceBib": "658", "sourceNat": "AUT", "rank": 7, "timeS": 800, "status": "ok"}, {"name": "Ochenbauer Angelina", "club": "HSV OL Wiener Neustadt", "timeText": "13:29", "sourceBib": "203", "sourceNat": "AUT", "rank": 8, "timeS": 809, "status": "ok"}, {"name": "Perktold Sabrina", "club": "Orienteering Innsbruck Imst", "timeText": "14:15", "sourceBib": "464", "sourceNat": "Imst AUT", "rank": 9, "timeS": 855, "status": "ok"}, {"name": "Witting Chiara", "club": "Orienteering Innsbruck Imst", "timeText": "14:45", "sourceBib": "480", "sourceNat": "Imst AUT", "rank": 10, "timeS": 885, "status": "ok"}, {"name": "Yevtushenko Yelyzaveta", "club": "Naturfreunde Wien", "timeText": "15:10", "sourceBib": "523", "sourceNat": "AUT", "rank": 11, "timeS": 910, "status": "ok"}, {"name": "Gruber Anna", "club": "HSV Ried", "timeText": "15:18", "sourceBib": "256", "sourceNat": "AUT", "rank": 12, "timeS": 918, "status": "ok"}, {"name": "Mitterer Lisa", "club": "ASKÖ Henndorf Orienteering", "timeText": "16:58", "sourceBib": "301", "sourceNat": "AUT", "rank": 13, "timeS": 1018, "status": "ok"}, {"name": "Berger Katja", "club": "Orienteering Klosterneuburg", "timeText": "17:24", "sourceBib": "239", "sourceNat": "AUT", "rank": 14, "timeS": 1044, "status": "ok"}, {"name": "Venhauer Alvina", "club": "OLCU Viktring", "timeText": "17:35", "sourceBib": "150", "sourceNat": "AUT", "rank": 15, "timeS": 1055, "status": "ok"}, {"name": "Beck Maria", "club": "Naturfreunde Wien", "timeText": "17:56", "sourceBib": "568", "sourceNat": "AUT", "rank": 16, "timeS": 1076, "status": "ok"}, {"name": "Brawisch Charlotte", "club": "HSV Wals", "timeText": "19:49", "sourceBib": "319", "sourceNat": "AUT", "rank": 17, "timeS": 1189, "status": "ok"}, {"name": "Winkler Sarina", "club": "Orienteering Innsbruck Imst", "timeText": "45:53", "sourceBib": "478", "sourceNat": "Imst AUT", "rank": 18, "timeS": 2753, "status": "ok"}, {"name": "Viertl Laurena", "club": "Naturfreunde Kitzbühel", "timeText": "Fehlst", "sourceBib": "499", "sourceNat": "AUT", "status": "mp"}, {"name": "Madl Eva", "club": "Orienteering Innsbruck Imst", "timeText": "N Ang", "sourceBib": "490", "sourceNat": "Imst AUT", "status": "dns"}], "courseLengthM": 1900, "courseClimbM": 50, "courseControls": 16}, {"name": "Damen ab 15 bis 18", "declaredStarters": 7, "results": [{"name": "Lueger Lena", "club": "SU Schöckl Orienteering", "timeText": "13:11", "sourceBib": "387", "sourceNat": "AUT", "rank": 1, "timeS": 791, "status": "ok"}, {"name": "Wieser Lara", "club": "Naturfreunde Kitzbühel", "timeText": "13:34", "sourceBib": "498", "sourceNat": "AUT", "rank": 2, "timeS": 814, "status": "ok"}, {"name": "Winkler Annika", "club": "SU Klagenfurt", "timeText": "13:45", "sourceBib": "161", "sourceNat": "AUT", "rank": 3, "timeS": 825, "status": "ok"}, {"name": "Sendlhofer Christiana", "club": "SU Klagenfurt", "timeText": "13:56", "sourceBib": "179", "sourceNat": "AUT", "rank": 4, "timeS": 836, "status": "ok"}, {"name": "Radon Zoe", "club": "Naturfreunde Wien", "timeText": "15:45", "sourceBib": "582", "sourceNat": "AUT", "rank": 5, "timeS": 945, "status": "ok"}, {"name": "Hartberger Hannah", "club": "FUN-OL NÖ", "timeText": "17:54", "sourceBib": "661", "sourceNat": "AUT", "rank": 6, "timeS": 1074, "status": "ok"}, {"name": "Mark Vanessa", "club": "Orienteering Innsbruck Imst", "timeText": "18:20", "sourceBib": "457", "sourceNat": "Imst AUT", "rank": 7, "timeS": 1100, "status": "ok"}], "courseLengthM": 1900, "courseClimbM": 40, "courseControls": 15}, {"name": "Damen ab 21 Lang", "declaredStarters": 6, "results": [{"name": "Englmaier Gudrun", "club": "OLC Wienerwald", "timeText": "13:07", "sourceBib": "598", "sourceNat": "AUT", "rank": 1, "timeS": 787, "status": "ok"}, {"name": "Glatz Verena", "club": "OLC Graz", "timeText": "14:11", "sourceBib": "364", "sourceNat": "AUT", "rank": 2, "timeS": 851, "status": "ok"}, {"name": "Kovarova Lenka", "club": "OLC Graz", "timeText": "14:43", "sourceBib": "350", "sourceNat": "AUT", "rank": 3, "timeS": 883, "status": "ok"}, {"name": "Kalcher Magdalena", "club": "HSV Pinkafeld", "timeText": "15:11", "sourceBib": "117", "sourceNat": "AUT", "rank": 4, "timeS": 911, "status": "ok"}, {"name": "Kalcher Hannah", "club": "HSV Pinkafeld", "timeText": "16:04", "sourceBib": "118", "sourceNat": "AUT", "rank": 5, "timeS": 964, "status": "ok"}, {"name": "Hoffmann Hannah", "club": "LZ OMAHA", "timeText": "16:47", "sourceBib": "121", "sourceNat": "AUT", "rank": 6, "timeS": 1007, "status": "ok"}], "courseLengthM": 2600, "courseClimbM": 75, "courseControls": 18}, {"name": "Damen ab 21 Kurz", "declaredStarters": 11, "results": [{"name": "Facinelli Sandra", "club": "SU Schöckl Orienteering", "timeText": "13:41", "sourceBib": "378", "sourceNat": "AUT", "rank": 1, "timeS": 821, "status": "ok"}, {"name": "Kelemen Bernadett", "club": "HSV OL Villach", "timeText": "13:58", "sourceBib": "138", "sourceNat": "AUT", "rank": 2, "timeS": 838, "status": "ok"}, {"name": "Obermüller Viktoria", "club": "Naturfreunde Linz", "timeText": "14:03", "sourceBib": "264", "sourceNat": "AUT", "rank": 3, "timeS": 843, "status": "ok"}, {"name": "Kaltenböck Marion", "club": "Naturfreunde Linz", "timeText": "15:26", "sourceBib": "271", "sourceNat": "AUT", "rank": 4, "timeS": 926, "status": "ok"}, {"name": "Kalcher Marie", "club": "HSV Pinkafeld", "timeText": "15:50", "sourceBib": "116", "sourceNat": "AUT", "rank": 5, "timeS": 950, "status": "ok"}, {"name": "Mayer Julia", "club": "HSV Großmittel", "timeText": "16:02", "sourceBib": "182", "sourceNat": "AUT", "rank": 6, "timeS": 962, "status": "ok"}, {"name": "Pregartner Delilah", "club": "SKV OLG Deutsch Kaltenbrunn", "timeText": "16:12", "sourceBib": "130", "sourceNat": "Kaltenbrunn AUT", "rank": 7, "timeS": 972, "status": "ok"}, {"name": "Benkovic Aneta", "club": "Orienteering Innsbruck Imst", "timeText": "17:32", "sourceBib": "440", "sourceNat": "Imst AUT", "rank": 8, "timeS": 1052, "status": "ok"}, {"name": "Neuwirth Annika", "club": "Orienteering Innsbruck Imst", "timeText": "18:21", "sourceBib": "460", "sourceNat": "Imst AUT", "rank": 9, "timeS": 1101, "status": "ok"}, {"name": "Witting Jasmin", "club": "Orienteering Innsbruck Imst", "timeText": "22:06", "sourceBib": "481", "sourceNat": "Imst AUT", "rank": 10, "timeS": 1326, "status": "ok"}, {"name": "Krail Katharina", "club": "WAT-OL", "timeText": "Disqu", "sourceBib": "619", "sourceNat": "AUT", "status": "dsq"}], "courseLengthM": 2300, "courseClimbM": 65, "courseControls": 15}, {"name": "Damen ab 35", "declaredStarters": 8, "results": [{"name": "Binder Ursula", "club": "SU Klagenfurt", "timeText": "11:20", "sourceBib": "165", "sourceNat": "AUT", "rank": 1, "timeS": 680, "status": "ok"}, {"name": "Hechl Isabel", "club": "Naturfreunde Kitzbühel", "timeText": "14:24", "sourceBib": "501", "sourceNat": "AUT", "rank": 2, "timeS": 864, "status": "ok"}, {"name": "Leonhardt Karin", "club": "OC Fürstenfeld", "timeText": "14:27", "sourceBib": "393", "sourceNat": "AUT", "rank": 3, "timeS": 867, "status": "ok"}, {"name": "Brodinger Franziska", "club": "ASKÖ Henndorf Orienteering", "timeText": "14:32", "sourceBib": "295", "sourceNat": "AUT", "rank": 4, "timeS": 872, "status": "ok"}, {"name": "Kennerknecht Stefanie", "club": "Naturfreunde Seekirchen", "timeText": "15:46", "sourceBib": "323", "sourceNat": "AUT", "rank": 5, "timeS": 946, "status": "ok"}, {"name": "Reindl Elena", "club": "SU Klagenfurt", "timeText": "26:13", "sourceBib": "176", "sourceNat": "AUT", "rank": 6, "timeS": 1573, "status": "ok"}, {"name": "Krail Elisabeth", "club": "WAT-OL", "timeText": "Fehlst", "sourceBib": "631", "sourceNat": "AUT", "status": "mp"}, {"name": "Morawec Sigrun", "club": "WAT-OL", "timeText": "N Ang", "sourceBib": "636", "sourceNat": "AUT", "status": "dns"}], "courseLengthM": 2300, "courseClimbM": 65, "courseControls": 15}, {"name": "Damen ab 40", "declaredStarters": 11, "results": [{"name": "Mair Christiana", "club": "Orienteering Innsbruck Imst", "timeText": "15:42", "sourceBib": "454", "sourceNat": "Imst AUT", "rank": 1, "timeS": 942, "status": "ok"}, {"name": "Tarnavska Iryna", "club": "Orienteering Innsbruck Imst", "timeText": "15:43", "sourceBib": "476", "sourceNat": "Imst AUT", "rank": 2, "timeS": 943, "status": "ok"}, {"name": "Kollndorfer Kathrin", "club": "HSV Großmittel", "timeText": "15:44", "sourceBib": "181", "sourceNat": "AUT", "rank": 3, "timeS": 944, "status": "ok"}, {"name": "Ochenbauer Nicole", "club": "HSV OL Wiener Neustadt", "timeText": "15:50", "sourceBib": "205", "sourceNat": "AUT", "rank": 4, "timeS": 950, "status": "ok"}, {"name": "Greiner-Löschnigg Irene", "club": "SU Schöckl Orienteering", "timeText": "17:22", "sourceBib": "383", "sourceNat": "AUT", "rank": 5, "timeS": 1042, "status": "ok"}, {"name": "Kaltenbacher Helga", "club": "HSV OL Wiener Neustadt", "timeText": "17:30", "sourceBib": "216", "sourceNat": "AUT", "rank": 6, "timeS": 1050, "status": "ok"}, {"name": "Piskorz Veronika", "club": "WAT-OL", "timeText": "17:44", "sourceBib": "624", "sourceNat": "AUT", "rank": 7, "timeS": 1064, "status": "ok"}, {"name": "Czech Verena", "club": "Orienteering Klosterneuburg", "timeText": "18:59", "sourceBib": "232", "sourceNat": "AUT", "rank": 8, "timeS": 1139, "status": "ok"}, {"name": "Meizer Susanna", "club": "SU Klagenfurt", "timeText": "19:15", "sourceBib": "173", "sourceNat": "AUT", "rank": 9, "timeS": 1155, "status": "ok"}, {"name": "Prader Sabine", "club": "HSV Pinkafeld", "timeText": "21:49", "sourceBib": "113", "sourceNat": "AUT", "rank": 10, "timeS": 1309, "status": "ok"}, {"name": "Hudax Tina", "club": "OC Fürstenfeld", "timeText": "24:43", "sourceBib": "396", "sourceNat": "AUT", "rank": 11, "timeS": 1483, "status": "ok"}], "courseLengthM": 2500, "courseClimbM": 60, "courseControls": 15}, {"name": "Damen ab 45", "declaredStarters": 26, "results": [{"name": "Rothauer Lucie", "club": "ASKÖ Henndorf Orienteering", "timeText": "12:36", "sourceBib": "306", "sourceNat": "AUT", "rank": 1, "timeS": 756, "status": "ok"}, {"name": "Kastner Barbara", "club": "Naturfreunde Wien", "timeText": "12:53", "sourceBib": "575", "sourceNat": "AUT", "rank": 2, "timeS": 773, "status": "ok"}, {"name": "Deixler-Thier Bettina", "club": "HSV Pinkafeld", "timeText": "15:24", "sourceBib": "120", "sourceNat": "AUT", "rank": 3, "timeS": 924, "status": "ok"}, {"name": "Calvet Christine", "club": "Naturfreunde Wien", "timeText": "15:32", "sourceBib": "529", "sourceNat": "AUT", "rank": 4, "timeS": 932, "status": "ok"}, {"name": "Gattringer Ingrid", "club": "HSV Ried", "timeText": "15:45", "sourceBib": "250", "sourceNat": "AUT", "rank": 5, "timeS": 945, "status": "ok"}, {"name": "Borsitzky Eva", "club": "HSV OL Wiener Neustadt", "timeText": "16:43", "sourceBib": "192", "sourceNat": "AUT", "rank": 6, "timeS": 1003, "status": "ok"}, {"name": "Tobler- Egger Gabriele", "club": "FUN-OL NÖ", "timeText": "16:58", "sourceBib": "656", "sourceNat": "AUT", "rank": 7, "timeS": 1018, "status": "ok"}, {"name": "Gindu-Ferrari Barbara", "club": "Orienteering Innsbruck Imst", "timeText": "17:08", "sourceBib": "445", "sourceNat": "Imst AUT", "rank": 8, "timeS": 1028, "status": "ok"}, {"name": "Mohn Monika", "club": "Leibnitzer AC OLG", "timeText": "17:21", "sourceBib": "340", "sourceNat": "AUT", "rank": 9, "timeS": 1041, "status": "ok"}, {"name": "Schönberger Carolin", "club": "ASKÖ Henndorf Orienteering", "timeText": "17:42", "sourceBib": "298", "sourceNat": "AUT", "rank": 10, "timeS": 1062, "status": "ok"}, {"name": "Urbanek Dinah", "club": "Naturfreunde Wien", "timeText": "17:46", "sourceBib": "524", "sourceNat": "AUT", "rank": 11, "timeS": 1066, "status": "ok"}, {"name": "Fischerleitner Karoline", "club": "HSV Ried", "timeText": "17:52", "sourceBib": "248", "sourceNat": "AUT", "rank": 12, "timeS": 1072, "status": "ok"}, {"name": "Skern Marina", "club": "Naturfreunde Wien", "timeText": "17:59", "sourceBib": "519", "sourceNat": "AUT", "rank": 13, "timeS": 1079, "status": "ok"}, {"name": "Gaudernak Elisabeth", "club": "OLT Transdanubien", "timeText": "18:01", "sourceBib": "608", "sourceNat": "AUT", "rank": 14, "timeS": 1081, "status": "ok"}, {"name": "Springer-Venhauer Sonja", "club": "OLCU Viktring", "timeText": "18:20", "sourceBib": "154", "sourceNat": "AUT", "rank": 15, "timeS": 1100, "status": "ok"}, {"name": "Madl Nina", "club": "Orienteering Innsbruck Imst", "timeText": "18:20", "sourceBib": "492", "sourceNat": "Imst AUT", "rank": 15, "timeS": 1100, "status": "ok"}, {"name": "Rapotz Brigitte", "club": "Naturfreunde Villach - Oriente", "timeText": "18:58", "sourceBib": "143", "sourceNat": "- Oriente AUT", "rank": 17, "timeS": 1138, "status": "ok"}, {"name": "Zangerle Kerstin", "club": "Orienteering Innsbruck Imst", "timeText": "19:43", "sourceBib": "484", "sourceNat": "Imst AUT", "rank": 18, "timeS": 1183, "status": "ok"}, {"name": "Venhauer-Rass Andrea", "club": "OLCU Viktring", "timeText": "20:19", "sourceBib": "152", "sourceNat": "AUT", "rank": 19, "timeS": 1219, "status": "ok"}, {"name": "Allwinger Judit", "club": "Leibnitzer AC OLG", "timeText": "20:35", "sourceBib": "327", "sourceNat": "AUT", "rank": 20, "timeS": 1235, "status": "ok"}, {"name": "Machold Natalia", "club": "Naturfreunde Wien", "timeText": "21:27", "sourceBib": "577", "sourceNat": "AUT", "rank": 21, "timeS": 1287, "status": "ok"}, {"name": "Perktold Barbara", "club": "Orienteering Innsbruck Imst", "timeText": "21:31", "sourceBib": "462", "sourceNat": "Imst AUT", "rank": 22, "timeS": 1291, "status": "ok"}, {"name": "Rass Julia", "club": "Orienteering Innsbruck Imst", "timeText": "24:34", "sourceBib": "467", "sourceNat": "Imst AUT", "rank": 23, "timeS": 1474, "status": "ok"}, {"name": "Dareb Andrea", "club": "SU Klagenfurt", "timeText": "25:21", "sourceBib": "168", "sourceNat": "AUT", "rank": 24, "timeS": 1521, "status": "ok"}, {"name": "Friedl-Steiner Susanne", "club": "HSV Pinkafeld", "timeText": "27:46", "sourceBib": "115", "sourceNat": "AUT", "rank": 25, "timeS": 1666, "status": "ok"}, {"name": "Klöckl Natalia", "club": "Orienteering Klosterneuburg", "timeText": "30:06", "sourceBib": "230", "sourceNat": "AUT", "rank": 26, "timeS": 1806, "status": "ok"}], "courseLengthM": 2500, "courseClimbM": 60, "courseControls": 15}, {"name": "Damen ab 50", "declaredStarters": 13, "results": [{"name": "Bonek Claudia", "club": "Naturfreunde Wien", "timeText": "13:24", "sourceBib": "553", "sourceNat": "AUT", "rank": 1, "timeS": 804, "status": "ok"}, {"name": "Fuchs Bati", "club": "FUN-OL NÖ", "timeText": "14:02", "sourceBib": "657", "sourceNat": "AUT", "rank": 2, "timeS": 842, "status": "ok"}, {"name": "Adenstedt Ingrid", "club": "Orienteering Klosterneuburg", "timeText": "14:03", "sourceBib": "223", "sourceNat": "AUT", "rank": 3, "timeS": 843, "status": "ok"}, {"name": "Zettl Karin", "club": "OLT Transdanubien", "timeText": "17:09", "sourceBib": "607", "sourceNat": "AUT", "rank": 4, "timeS": 1029, "status": "ok"}, {"name": "Vogl Karin", "club": "ASKÖ Henndorf Orienteering", "timeText": "18:19", "sourceBib": "276", "sourceNat": "AUT", "rank": 5, "timeS": 1099, "status": "ok"}, {"name": "Wolfram-Teischl Sabine", "club": "Naturfreunde Wien", "timeText": "18:27", "sourceBib": "537", "sourceNat": "AUT", "rank": 6, "timeS": 1107, "status": "ok"}, {"name": "Aigmüller Martina", "club": "SU Schöckl Orienteering", "timeText": "18:46", "sourceBib": "384", "sourceNat": "AUT", "rank": 7, "timeS": 1126, "status": "ok"}, {"name": "Walch Karin", "club": "OLC Graz", "timeText": "19:42", "sourceBib": "346", "sourceNat": "AUT", "rank": 8, "timeS": 1182, "status": "ok"}, {"name": "Kovacs Margit", "club": "OLT Transdanubien", "timeText": "20:16", "sourceBib": "605", "sourceNat": "AUT", "rank": 9, "timeS": 1216, "status": "ok"}, {"name": "Kaminger Ingrid", "club": "Orienteering Klosterneuburg", "timeText": "21:00", "sourceBib": "219", "sourceNat": "AUT", "rank": 10, "timeS": 1260, "status": "ok"}, {"name": "Nesitka Doris", "club": "SU Schöckl Orienteering", "timeText": "24:34", "sourceBib": "390", "sourceNat": "AUT", "rank": 11, "timeS": 1474, "status": "ok"}, {"name": "Dornstauder Sandra", "club": "HSV OL Wiener Neustadt", "timeText": "28:49", "sourceBib": "198", "sourceNat": "AUT", "rank": 12, "timeS": 1729, "status": "ok"}, {"name": "Pegan Bernadett", "club": "Naturfreunde Villach - Orienteering", "timeText": "Fehlst", "sourceBib": "141", "sourceNat": "- Oriente AUT", "status": "mp"}], "courseLengthM": 2100, "courseClimbM": 45, "courseControls": 12}, {"name": "Damen ab 55", "declaredStarters": 22, "results": [{"name": "Wlcek Sonja", "club": "WAT-OL", "timeText": "12:49", "sourceBib": "611", "sourceNat": "AUT", "rank": 1, "timeS": 769, "status": "ok"}, {"name": "Hillebrand Karin", "club": "ASKÖ Henndorf Orienteering", "timeText": "12:56", "sourceBib": "289", "sourceNat": "AUT", "rank": 2, "timeS": 776, "status": "ok"}, {"name": "Berger Hedi", "club": "Orienteering Klosterneuburg", "timeText": "12:57", "sourceBib": "238", "sourceNat": "AUT", "rank": 3, "timeS": 777, "status": "ok"}, {"name": "Arbter Vera", "club": "Naturfreunde Wien", "timeText": "13:12", "sourceBib": "552", "sourceNat": "AUT", "rank": 4, "timeS": 792, "status": "ok"}, {"name": "Eschlböck Gudrun", "club": "Naturfreunde Linz", "timeText": "15:47", "sourceBib": "260", "sourceNat": "AUT", "rank": 5, "timeS": 947, "status": "ok"}, {"name": "Glatz Sylvia", "club": "OLC Graz", "timeText": "16:01", "sourceBib": "363", "sourceNat": "AUT", "rank": 6, "timeS": 961, "status": "ok"}, {"name": "Gassner Katja", "club": "Naturfreunde Wien", "timeText": "16:24", "sourceBib": "566", "sourceNat": "AUT", "rank": 7, "timeS": 984, "status": "ok"}, {"name": "Biel-Pretting Renate", "club": "Naturfreunde Wien", "timeText": "16:48", "sourceBib": "561", "sourceNat": "AUT", "rank": 8, "timeS": 1008, "status": "ok"}, {"name": "Gittmaier Doris", "club": "HSV Ried", "timeText": "17:54", "sourceBib": "257", "sourceNat": "AUT", "rank": 9, "timeS": 1074, "status": "ok"}, {"name": "Palme Guni", "club": "OLC Wienerwald", "timeText": "17:59", "sourceBib": "593", "sourceNat": "AUT", "rank": 10, "timeS": 1079, "status": "ok"}, {"name": "Egarter Michaela", "club": "OC Fürstenfeld", "timeText": "18:35", "sourceBib": "400", "sourceNat": "AUT", "rank": 11, "timeS": 1115, "status": "ok"}, {"name": "Zöbl Maria", "club": "Naturfreunde Linz", "timeText": "18:45", "sourceBib": "265", "sourceNat": "AUT", "rank": 12, "timeS": 1125, "status": "ok"}, {"name": "Tiefenböck Riki", "club": "Naturfreunde Wien", "timeText": "18:46", "sourceBib": "548", "sourceNat": "AUT", "rank": 13, "timeS": 1126, "status": "ok"}, {"name": "Berger Gislind", "club": "Orienteering Klosterneuburg", "timeText": "19:06", "sourceBib": "218", "sourceNat": "AUT", "rank": 14, "timeS": 1146, "status": "ok"}, {"name": "Lueger Ingrid", "club": "SU Schöckl Orienteering", "timeText": "20:00", "sourceBib": "380", "sourceNat": "AUT", "rank": 15, "timeS": 1200, "status": "ok"}, {"name": "Hackl Claudia", "club": "ASKÖ Henndorf Orienteering", "timeText": "20:02", "sourceBib": "286", "sourceNat": "AUT", "rank": 16, "timeS": 1202, "status": "ok"}, {"name": "Elstner Margit", "club": "ASKÖ Henndorf Orienteering", "timeText": "21:28", "sourceBib": "285", "sourceNat": "AUT", "rank": 17, "timeS": 1288, "status": "ok"}, {"name": "Wagner Birgit", "club": "Naturfreunde Linz", "timeText": "22:45", "sourceBib": "261", "sourceNat": "AUT", "rank": 18, "timeS": 1365, "status": "ok"}, {"name": "Hofstätter Sabine", "club": "Naturfreunde Wien", "timeText": "26:20", "sourceBib": "572", "sourceNat": "AUT", "rank": 19, "timeS": 1580, "status": "ok"}, {"name": "Maget Brigitte", "club": "SKV OLG Deutsch Kaltenbrunn", "timeText": "36:37", "sourceBib": "129", "sourceNat": "Kaltenbrunn AUT", "rank": 20, "timeS": 2197, "status": "ok"}, {"name": "Kirchmeir Elisabeth", "club": "HSV OL Wiener Neustadt", "timeText": "N Ang", "sourceBib": "199", "sourceNat": "AUT", "status": "dns"}, {"name": "Scholl-Bürgi Sabine", "club": "HSV Absam OL", "timeText": "N Ang", "sourceBib": "428", "sourceNat": "AUT", "status": "dns"}], "courseLengthM": 2100, "courseClimbM": 45, "courseControls": 12}, {"name": "Damen ab 60", "declaredStarters": 7, "results": [{"name": "Strobl Helene", "club": "HSV Pinkafeld", "timeText": "14:20", "sourceBib": "107", "sourceNat": "AUT", "rank": 1, "timeS": 860, "status": "ok"}, {"name": "Gassner Irene", "club": "Naturfreunde Wien", "timeText": "15:49", "sourceBib": "550", "sourceNat": "AUT", "rank": 2, "timeS": 949, "status": "ok"}, {"name": "Pamlitschka Herta", "club": "WAT-OL", "timeText": "15:53", "sourceBib": "622", "sourceNat": "AUT", "rank": 3, "timeS": 953, "status": "ok"}, {"name": "Schreiber Hannelore", "club": "HSV Langenlebarn", "timeText": "17:48", "sourceBib": "188", "sourceNat": "AUT", "rank": 4, "timeS": 1068, "status": "ok"}, {"name": "Kröppl Elke", "club": "HSV Großmittel", "timeText": "17:57", "sourceBib": "183", "sourceNat": "AUT", "rank": 5, "timeS": 1077, "status": "ok"}, {"name": "Oswald Angelika", "club": "HSV Pinkafeld", "timeText": "23:10", "sourceBib": "103", "sourceNat": "AUT", "rank": 6, "timeS": 1390, "status": "ok"}, {"name": "Mayer Brigitta", "club": "HSV Großmittel", "timeText": "25:02", "sourceBib": "184", "sourceNat": "AUT", "rank": 7, "timeS": 1502, "status": "ok"}], "courseLengthM": 1700, "courseClimbM": 50, "courseControls": 12}, {"name": "Damen ab 65", "declaredStarters": 8, "results": [{"name": "Irk Karin", "club": "Naturfreunde Villach - Oriente", "timeText": "14:25", "sourceBib": "140", "sourceNat": "- Oriente AUT", "rank": 1, "timeS": 865, "status": "ok"}, {"name": "Oswald Luise", "club": "HSV Pinkafeld", "timeText": "15:55", "sourceBib": "112", "sourceNat": "AUT", "rank": 2, "timeS": 955, "status": "ok"}, {"name": "Leonhardt Gertraud", "club": "OC Fürstenfeld", "timeText": "18:11", "sourceBib": "408", "sourceNat": "AUT", "rank": 3, "timeS": 1091, "status": "ok"}, {"name": "Nilsson Gunnel", "club": "OLC Wienerwald", "timeText": "20:07", "sourceBib": "601", "sourceNat": "AUT", "rank": 4, "timeS": 1207, "status": "ok"}, {"name": "Ponweiser Christine", "club": "HSV OL Wiener Neustadt", "timeText": "20:08", "sourceBib": "209", "sourceNat": "AUT", "rank": 5, "timeS": 1208, "status": "ok"}, {"name": "Ziegerhofer Anneliese", "club": "Naturfreunde Linz", "timeText": "20:47", "sourceBib": "268", "sourceNat": "AUT", "rank": 6, "timeS": 1247, "status": "ok"}, {"name": "Schanz Frieda", "club": "Leibnitzer AC OLG", "timeText": "22:37", "sourceBib": "344", "sourceNat": "AUT", "rank": 7, "timeS": 1357, "status": "ok"}, {"name": "Bosina Inge", "club": "Naturfreunde Wien", "timeText": "24:59", "sourceBib": "584", "sourceNat": "AUT", "rank": 8, "timeS": 1499, "status": "ok"}], "courseLengthM": 1700, "courseClimbM": 50, "courseControls": 12}, {"name": "Damen ab 70", "declaredStarters": 3, "results": [{"name": "Knapp Elisabeth", "club": "Orienteering Klosterneuburg", "timeText": "10:05", "sourceBib": "233", "sourceNat": "AUT", "rank": 1, "timeS": 605, "status": "ok"}, {"name": "Linhart Reingild", "club": "HSV OL Wiener Neustadt", "timeText": "11:55", "sourceBib": "201", "sourceNat": "AUT", "rank": 2, "timeS": 715, "status": "ok"}, {"name": "Prommer Martha", "club": "Naturfreunde Villach - Orienteering", "timeText": "Fehlst", "sourceBib": "145", "sourceNat": "- Oriente AUT", "status": "mp"}], "courseLengthM": 1400, "courseClimbM": 35, "courseControls": 14}, {"name": "Damen ab 75", "declaredStarters": 4, "results": [{"name": "Roder Ulrike", "club": "HSV Ried", "timeText": "14:26", "sourceBib": "253", "sourceNat": "AUT", "rank": 1, "timeS": 866, "status": "ok"}, {"name": "Venhauer Dieti", "club": "OLCU Viktring", "timeText": "16:50", "sourceBib": "149", "sourceNat": "AUT", "rank": 2, "timeS": 1010, "status": "ok"}, {"name": "Müller Brigitte", "club": "ASKÖ Henndorf Orienteering", "timeText": "19:09", "sourceBib": "278", "sourceNat": "AUT", "rank": 3, "timeS": 1149, "status": "ok"}, {"name": "Rass Elisabeth", "club": "Orienteering Innsbruck Imst", "timeText": "21:23", "sourceBib": "466", "sourceNat": "Imst AUT", "rank": 4, "timeS": 1283, "status": "ok"}], "courseLengthM": 1400, "courseClimbM": 35, "courseControls": 14}, {"name": "Damen Hobby", "declaredStarters": 7, "results": [{"name": "Imriska Jana", "club": "Naturfreunde Wien", "timeText": "14:27", "sourceBib": "540", "sourceNat": "AUT", "rank": 1, "timeS": 867, "status": "ok"}, {"name": "Brabek Eva", "club": "OC Fürstenfeld", "timeText": "17:07", "sourceBib": "424", "sourceNat": "AUT", "rank": 2, "timeS": 1027, "status": "ok"}, {"name": "Kofler Corinna", "club": "HSV OL Villach", "timeText": "18:19", "sourceBib": "135", "sourceNat": "AUT", "rank": 3, "timeS": 1099, "status": "ok"}, {"name": "Kaiser Isabell", "club": "Naturfreunde Kitzbühel", "timeText": "19:04", "sourceBib": "507", "sourceNat": "AUT", "rank": 4, "timeS": 1144, "status": "ok"}, {"name": "Ujvari Sandra", "club": "Naturfreunde Wien", "timeText": "19:43", "sourceBib": "515", "sourceNat": "AUT", "rank": 5, "timeS": 1183, "status": "ok"}, {"name": "Ebster Tanja", "club": "ASKÖ Henndorf Orienteering", "timeText": "22:03", "sourceBib": "305", "sourceNat": "AUT", "rank": 6, "timeS": 1323, "status": "ok"}, {"name": "Lechner Claudia", "club": "HSV Wals", "timeText": "24:23", "sourceBib": "322", "sourceNat": "AUT", "rank": 7, "timeS": 1463, "status": "ok"}], "courseLengthM": 1900, "courseClimbM": 40, "courseControls": 15}, {"name": "Offen Lang", "declaredStarters": 8, "results": [{"name": "Keuschnigg Peter", "club": "OL Kufstein", "timeText": "15:13", "sourceBib": "642", "sourceNat": "AUT", "rank": 1, "timeS": 913, "status": "ok"}, {"name": "Rothauer Thomas", "club": "ASKÖ Henndorf Orienteering", "timeText": "15:47", "sourceBib": "307", "sourceNat": "AUT", "rank": 2, "timeS": 947, "status": "ok"}, {"name": "Sova Oleksandr", "club": "OL Kufstein", "timeText": "18:01", "sourceBib": "653", "sourceNat": "AUT", "rank": 3, "timeS": 1081, "status": "ok"}, {"name": "Bancalari Jakob", "club": "SU Schöckl Orienteering", "timeText": "22:15", "sourceBib": "392", "sourceNat": "AUT", "rank": 4, "timeS": 1335, "status": "ok"}, {"name": "Mumelter Helene", "club": "OL Kufstein", "timeText": "23:15", "sourceBib": "639", "sourceNat": "AUT", "rank": 5, "timeS": 1395, "status": "ok"}, {"name": "Schönberger Martin", "club": "ASKÖ Henndorf Orienteering", "timeText": "23:55", "sourceBib": "300", "sourceNat": "AUT", "rank": 6, "timeS": 1435, "status": "ok"}, {"name": "Winter Larissa", "club": "OL Kufstein", "timeText": "31:06", "sourceBib": "640", "sourceNat": "AUT", "rank": 7, "timeS": 1866, "status": "ok"}, {"name": "Gruber Claudia", "club": "Naturfreunde Linz", "timeText": "38:22", "sourceBib": "274", "sourceNat": "AUT", "rank": 8, "timeS": 2302, "status": "ok"}], "courseLengthM": 2600, "courseClimbM": 75, "courseControls": 18}, {"name": "Offen Kurz", "declaredStarters": 9, "results": [{"name": "Kasper Ida-Karolina", "club": "LZ OMAHA", "timeText": "11:40", "sourceBib": "123", "sourceNat": "AUT", "rank": 1, "timeS": 700, "status": "ok"}, {"name": "Kröppl Katrin", "club": "HSV Großmittel", "timeText": "14:30", "sourceBib": "185", "sourceNat": "AUT", "rank": 2, "timeS": 870, "status": "ok"}, {"name": "Klöckl Günther", "club": "Orienteering Klosterneuburg", "timeText": "15:19", "sourceBib": "221", "sourceNat": "AUT", "rank": 3, "timeS": 919, "status": "ok"}, {"name": "Palma Max", "club": "Orienteering Innsbruck Imst", "timeText": "16:23", "sourceBib": "461", "sourceNat": "Imst AUT", "rank": 4, "timeS": 983, "status": "ok"}, {"name": "Zapf Manfrd", "club": "OC Fürstenfeld", "timeText": "17:10", "sourceBib": "983", "sourceNat": "AUT", "rank": 5, "timeS": 1030, "status": "ok"}, {"name": "Zapf Christa", "club": "OC Fürstenfeld", "timeText": "17:21", "sourceBib": "982", "sourceNat": "AUT", "rank": 6, "timeS": 1041, "status": "ok"}, {"name": "Mayrhofer Klaudia", "club": "SKV OLG Deutsch Kaltenbrunn", "timeText": "18:40", "sourceBib": "127", "sourceNat": "Kaltenbrunn AUT", "rank": 7, "timeS": 1120, "status": "ok"}, {"name": "Keuschnigg-Koller Silvia", "club": "OL Kufstein", "timeText": "24:00", "sourceBib": "643", "sourceNat": "AUT", "rank": 8, "timeS": 1440, "status": "ok"}, {"name": "Gaar-Paier Doris", "club": "WAT-OL", "timeText": "29:43", "sourceBib": "613", "sourceNat": "AUT", "rank": 9, "timeS": 1783, "status": "ok"}], "courseLengthM": 2000, "courseClimbM": 45, "courseControls": 17}, {"name": "Neulinge", "declaredStarters": 8, "results": [{"name": "Tabernig Amon", "club": "Orienteering Innsbruck Imst", "timeText": "15:26", "sourceBib": "992", "sourceNat": "Imst AUT", "rank": 1, "timeS": 926, "status": "ok"}, {"name": "Nindl Tanja", "club": "Naturfreunde Kitzbühel", "timeText": "15:30", "sourceBib": "505", "sourceNat": "AUT", "rank": 2, "timeS": 930, "status": "ok"}, {"name": "Maiorenko Karolina", "club": "Naturfreunde Wien", "timeText": "16:07", "sourceBib": "592", "sourceNat": "AUT", "rank": 3, "timeS": 967, "status": "ok"}, {"name": "Gstrein Janine", "club": "Orienteering Innsbruck Imst", "timeText": "47:32", "sourceBib": "493", "sourceNat": "Imst AUT", "rank": 4, "timeS": 2852, "status": "ok"}, {"name": "Maiorenko Olena", "club": "Naturfreunde Wien", "timeText": "Fehlst", "sourceBib": "591", "sourceNat": "AUT", "status": "mp"}, {"name": "Stangl Ernst", "club": "WAT-OL", "timeText": "Aufg", "sourceBib": "993", "sourceNat": "AUT", "status": "dnf"}, {"name": "Drizo Tetiana", "club": "Naturfreunde Wien", "timeText": "N Ang", "sourceBib": "587", "sourceNat": "AUT", "status": "dns"}, {"name": "Orleth Walter", "club": "Naturfreunde Wien", "timeText": "N Ang", "sourceBib": "589", "sourceNat": "AUT", "status": "dns"}], "courseLengthM": 1900, "courseClimbM": 30, "courseControls": 18}, {"name": "Familie", "declaredStarters": 12, "results": [{"name": "Schöpf Lukas + Martin", "club": "Orienteering Innsbruck Imst", "timeText": "11:04", "sourceBib": "996", "sourceNat": "Imst AUT", "rank": 1, "timeS": 664, "status": "ok"}, {"name": "Borsitzky Tobias", "club": "HSV OL Wiener Neustadt", "timeText": "16:00", "sourceBib": "195", "sourceNat": "AUT", "rank": 2, "timeS": 960, "status": "ok"}, {"name": "Wittberger Luis", "club": "HSV OL Wiener Neustadt", "timeText": "16:07", "sourceBib": "215", "sourceNat": "AUT", "rank": 3, "timeS": 967, "status": "ok"}, {"name": "Chirinos-Ujvari Lucia", "club": "Naturfreunde Wien", "timeText": "20:59", "sourceBib": "516", "sourceNat": "AUT", "rank": 4, "timeS": 1259, "status": "ok"}, {"name": "Hudax Henrik", "club": "OC Fürstenfeld", "timeText": "21:01", "sourceBib": "397", "sourceNat": "AUT", "rank": 5, "timeS": 1261, "status": "ok"}, {"name": "Melkes Zina", "club": "OL Kufstein", "timeText": "22:41", "sourceBib": "651", "sourceNat": "AUT", "rank": 6, "timeS": 1361, "status": "ok"}, {"name": "Springer Annika", "club": "OLCU Viktring", "timeText": "22:55", "sourceBib": "155", "sourceNat": "AUT", "rank": 7, "timeS": 1375, "status": "ok"}, {"name": "Gattringer Valentin", "club": "HSV Ried", "timeText": "24:17", "sourceBib": "252", "sourceNat": "AUT", "rank": 8, "timeS": 1457, "status": "ok"}, {"name": "Keuschnigg Moritz", "club": "OL Kufstein", "timeText": "27:31", "sourceBib": "644", "sourceNat": "AUT", "rank": 9, "timeS": 1651, "status": "ok"}, {"name": "Krail Timna", "club": "WAT-OL", "timeText": "37:12", "sourceBib": "632", "sourceNat": "AUT", "rank": 10, "timeS": 2232, "status": "ok"}, {"name": "Dobler Oskar", "club": "MTV Hernals", "timeText": "37:38", "sourceBib": "998", "sourceNat": "AUT", "rank": 11, "timeS": 2258, "status": "ok"}, {"name": "Rothauer Emma", "club": "ASKÖ Henndorf Orienteering", "timeText": "41:18", "sourceBib": "309", "sourceNat": "AUT", "rank": 12, "timeS": 2478, "status": "ok"}], "courseLengthM": 1900, "courseClimbM": 30, "courseControls": 18}]}