{"eventId": 4723, "source": "sportsoftware-pdf", "sourceUrl": "https://anne-cdn.oefol.at/public/legacy/event_4723_erg171024.pdf", "fileName": "event_4723_erg171024.pdf", "listType": "race", "docDate": "2024-10-17", "categories": [{"name": "Unterstufe weiblich", "declaredStarters": 18, "results": [{"name": "Varga Sarah", "club": "BG/BRG Oberschützen", "timeText": "18:45", "rank": 1, "timeS": 1125, "status": "ok", "yearOfBirth": 2010}, {"name": "Huber Pia", "club": "BG/BRG Oberschützen", "timeText": "21:13", "rank": 2, "timeS": 1273, "status": "ok", "yearOfBirth": 2011}, {"name": "Zach Sissi", "club": "MS Rudersdorf", "timeText": "21:46", "rank": 3, "timeS": 1306, "status": "ok", "yearOfBirth": 2013}, {"name": "Schuh Valentina", "club": "BG/BRG Oberschützen", "timeText": "21:59", "rank": 4, "timeS": 1319, "status": "ok", "yearOfBirth": 2012}, {"name": "Oswald Emma", "club": "Wimmer Gym Oberschützen", "timeText": "22:25", "rank": 5, "timeS": 1345, "status": "ok", "yearOfBirth": 2012}, {"name": "Glatz Anika", "club": "BG/BRG Oberschützen", "timeText": "27:10", "rank": 6, "timeS": 1630, "status": "ok", "yearOfBirth": 2011}, {"name": "Benedek Paula", "club": "Wimmer Gym Oberschützen", "timeText": "29:55", "rank": 7, "timeS": 1795, "status": "ok", "yearOfBirth": 2011}, {"name": "Hofer Emma", "club": "BG/BRG Oberschützen", "timeText": "30:28", "rank": 8, "timeS": 1828, "status": "ok", "yearOfBirth": 2011}, {"name": "Tauss Jana", "club": "BG/BRG Oberschützen", "timeText": "31:14", "rank": 9, "timeS": 1874, "status": "ok", "yearOfBirth": 2012}, {"name": "Misik Amelie", "club": "Wimmer Gym Oberschützen", "timeText": "32:18", "rank": 10, "timeS": 1938, "status": "ok", "yearOfBirth": 2010}, {"name": "Kaplan Johanna", "club": "BG/BRG Oberschützen", "timeText": "35:06", "rank": 11, "timeS": 2106, "status": "ok", "yearOfBirth": 2011}, {"name": "Schmaldienst Annabell", "club": "MS Rudersdorf", "timeText": "36:19", "rank": 12, "timeS": 2179, "status": "ok", "yearOfBirth": 2011}, {"name": "Käfer Lina", "club": "Wimmer Gym Oberschützen", "timeText": "44:43", "rank": 13, "timeS": 2683, "status": "ok", "yearOfBirth": 2011}, {"name": "Roth Mimi", "club": "Wimmer Gym Oberschützen", "timeText": "47:29", "rank": 14, "timeS": 2849, "status": "ok", "yearOfBirth": 2011}, {"name": "Gölles Alissa", "club": "MS Rudersdorf", "timeText": "51:28", "rank": 15, "timeS": 3088, "status": "ok", "yearOfBirth": 2011}, {"name": "Korsalka Charlene", "club": "Wimmer Gym Oberschützen", "timeText": "Fehlst", "status": "mp", "yearOfBirth": 2010}, {"name": "Urbauer Lea", "club": "Wimmer Gym Oberschützen", "timeText": "N Ang", "status": "dns", "yearOfBirth": 2012}, {"name": "Pinter Mia", "club": "BG/BRG Oberschützen", "timeText": "N Ang", "status": "dns", "yearOfBirth": 2011}], "courseLengthM": 1800, "courseClimbM": 45, "courseControls": 12}, {"name": "Unterstufe männlich", "declaredStarters": 12, "results": [{"name": "Schuh Leonard", "club": "BG/BRG Oberschützen", "timeText": "18:43", "rank": 1, "timeS": 1123, "status": "ok", "yearOfBirth": 2010}, {"name": "Prader Johannes", "club": "BG/BRG Oberschützen", "timeText": "22:13", "rank": 2, "timeS": 1333, "status": "ok", "yearOfBirth": 2011}, {"name": "Windhofer Leo", "club": "BG/BRG Oberschützen", "timeText": "32:49", "rank": 3, "timeS": 1969, "status": "ok", "yearOfBirth": 2010}, {"name": "Fürst Peter", "club": "Wimmer Gym Oberschützen", "timeText": "37:30", "rank": 4, "timeS": 2250, "status": "ok", "yearOfBirth": 2011}, {"name": "Giessauf Jonas", "club": "MS Rudersdorf", "timeText": "39:40", "rank": 5, "timeS": 2380, "status": "ok", "yearOfBirth": 2011}, {"name": "Lackner Daniel", "club": "BG/BRG Oberschützen", "timeText": "43:46", "rank": 6, "timeS": 2626, "status": "ok", "yearOfBirth": 2013}, {"name": "Beiglböck Finn", "club": "SMS Oberschützen", "timeText": "48:04", "rank": 7, "timeS": 2884, "status": "ok"}, {"name": "Schmaldienst Simon", "club": "MS Rudersdorf", "timeText": "54:50", "rank": 8, "timeS": 3290, "status": "ok", "yearOfBirth": 2013}, {"name": "Weninger Michael", "club": "Wimmer Gym Oberschützen", "timeText": "Fehlst", "status": "mp", "yearOfBirth": 2011}, {"name": "Frey Finn", "club": "SMS Oberschützen", "timeText": "Fehlst", "status": "mp"}, {"name": "Kahr Elias", "club": "SMS Oberschützen", "timeText": "Fehlst", "status": "mp"}, {"name": "Nemeth Nino", "club": "BG/BRG Oberschützen", "timeText": "N Ang", "status": "dns", "yearOfBirth": 2012}], "courseLengthM": 2000, "courseClimbM": 80, "courseControls": 12}, {"name": "Oberstufe weiblich", "declaredStarters": 5, "results": [{"name": "Stark Valentina", "club": "BG/BRG Oberschützen", "timeText": "44:20", "rank": 1, "timeS": 2660, "status": "ok", "yearOfBirth": 2008}, {"name": "Nierer Elena", "club": "Business Campus", "timeText": "1:06:46", "rank": 2, "timeS": 4006, "status": "ok", "yearOfBirth": 2010}, {"name": "Huss Julia", "club": "Wimmer Gym Oberschützen", "timeText": "Fehlst", "status": "mp", "yearOfBirth": 2010}, {"name": "Plank Ina", "club": "Wimmer Gym Oberschützen", "timeText": "Aufg", "status": "dnf", "yearOfBirth": 2010}, {"name": "Hofer Chiara", "club": "Wimmer Gym Oberschützen", "timeText": "Aufg", "status": "dnf", "yearOfBirth": 2009}], "courseLengthM": 2900, "courseClimbM": 105, "courseControls": 13}, {"name": "Oberstufe männlich", "declaredStarters": 21, "results": [{"name": "Schmallhardt Matthias", "club": "HTL Pinkafeld", "timeText": "25:57", "rank": 1, "timeS": 1557, "status": "ok", "yearOfBirth": 2009}, {"name": "Kogelmann Simon", "club": "HTL Pinkafeld", "timeText": "37:58", "rank": 2, "timeS": 2278, "status": "ok", "yearOfBirth": 2007}, {"name": "Prader Philipp", "club": "HTL Pinkafeld", "timeText": "39:47", "rank": 3, "timeS": 2387, "status": "ok", "yearOfBirth": 2007}, {"name": "Lex John", "club": "BORG Jennersdorf", "timeText": "44:50", "rank": 4, "timeS": 2690, "status": "ok", "yearOfBirth": 2008}, {"name": "Rotheneder Phillip", "club": "HTL Pinkafeld", "timeText": "48:53", "rank": 5, "timeS": 2933, "status": "ok", "yearOfBirth": 2007}, {"name": "Spanring Michael", "club": "HTL Pinkafeld", "timeText": "50:40", "rank": 6, "timeS": 3040, "status": "ok", "yearOfBirth": 2007}, {"name": "Gartner Sebastian", "club": "BORG Jennersdorf", "timeText": "57:00", "rank": 7, "timeS": 3420, "status": "ok", "yearOfBirth": 2008}, {"name": "Berghold Toni", "club": "BORG Jennersdorf", "timeText": "1:00:36", "rank": 8, "timeS": 3636, "status": "ok", "yearOfBirth": 2008}, {"name": "Kertesz Florian", "club": "BORG Jennersdorf", "timeText": "1:01:13", "rank": 9, "timeS": 3673, "status": "ok", "yearOfBirth": 2008}, {"name": "Tropper Jonas", "club": "BORG Jennersdorf", "timeText": "1:02:28", "rank": 10, "timeS": 3748, "status": "ok", "yearOfBirth": 2007}, {"name": "Deutsch Felix", "club": "BORG Jennersdorf", "timeText": "1:05:23", "rank": 11, "timeS": 3923, "status": "ok", "yearOfBirth": 2008}, {"name": "Schriefl Nicolas", "club": "BG/BRG Oberschützen", "timeText": "1:20:43", "rank": 12, "timeS": 4843, "status": "ok", "yearOfBirth": 2008}, {"name": "Raiser Julian", "club": "BORG Jennersdorf", "timeText": "1:30:53", "rank": 13, "timeS": 5453, "status": "ok", "yearOfBirth": 2009}, {"name": "Seidl Tobias", "club": "BORG Jennersdorf", "timeText": "Fehlst", "status": "mp", "yearOfBirth": 2008}, {"name": "Ilie Rares", "club": "HTL Pinkafeld", "timeText": "Fehlst", "status": "mp", "yearOfBirth": 2008}, {"name": "Linde Dario", "club": "BORG Jennersdorf", "timeText": "Fehlst", "status": "mp", "yearOfBirth": 2008}, {"name": "Lababidir Monir", "club": "BORG Jennersdorf", "timeText": "Aufg", "status": "dnf", "yearOfBirth": 2008}, {"name": "Schenk Andre", "club": "BORG Jennersdorf", "timeText": "Aufg", "status": "dnf", "yearOfBirth": 2009}, {"name": "Johnson Anthony", "club": "BORG Jennersdorf", "timeText": "N Ang", "status": "dns", "yearOfBirth": 2007}, {"name": "Wagner Maximilian", "club": "HTL Pinkafeld", "timeText": "N Ang", "status": "dns", "yearOfBirth": 2006}, {"name": "Bärnschütz Stefan", "club": "HTL Pinkafeld", "timeText": "N Ang", "status": "dns", "yearOfBirth": 2009}], "courseLengthM": 3100, "courseClimbM": 110, "courseControls": 17}, {"name": "Schnupper (Unterstufe)", "declaredStarters": 17, "results": [{"name": "Ondrejcáková Hana", "club": "BG/BRG Oberschützen", "timeText": "22:44", "rank": 1, "timeS": 1364, "status": "ok", "yearOfBirth": 2011}, {"name": "Artner/Csencsits", "club": "SMS Oberschützen", "timeText": "29:01", "rank": 2, "timeS": 1741, "status": "ok"}, {"name": "Ratz/Zlatarits Jonathan/Johann", "club": "SMS Oberschützen", "timeText": "38:57", "rank": 3, "timeS": 2337, "status": "ok"}, {"name": "Parapatits/Halwachs", "club": "BG/BRG Oberschützen", "timeText": "44:37", "rank": 4, "timeS": 2677, "status": "ok"}, {"name": "Nemesi-Mitterstiller/Mus", "club": "Oberschützen", "timeText": "54:07", "rank": 5, "timeS": 3247, "status": "ok"}, {"name": "7 Feichtinger/Hübner/", "club": "SMS Güssing", "timeText": "1:25:07", "rank": 6, "timeS": 5107, "status": "ok"}, {"name": "Stangl/Pfeiffer Sophie/Naemi", "club": "Wimmer Gym Oberschützen", "timeText": "1:28:32", "rank": 7, "timeS": 5312, "status": "ok", "yearOfBirth": 2011}, {"name": "Air/Germ/ Schlaffer", "club": "SMS Güssing", "timeText": "1:37:04", "rank": 8, "timeS": 5824, "status": "ok", "yearOfBirth": 2012}, {"name": "4 Messenlehner/Szerencsits", "club": "SMS Güssing", "timeText": "1:41:11", "rank": 9, "timeS": 6071, "status": "ok"}, {"name": "Hammer/Potokovic/", "club": "SMS Güssing", "timeText": "Fehlst", "rank": 3, "status": "mp"}, {"name": "Antonicek/Url/ Weidinger", "club": "SMS Güssing", "timeText": "Fehlst", "rank": 1, "status": "mp", "yearOfBirth": 2013}, {"name": "Lukács/Mikovits/", "club": "SMS Güssing", "timeText": "Fehlst", "rank": 5, "status": "mp"}, {"name": "Breyer/Neubauer-Szerencs", "club": "Güssing", "timeText": "Fehlst", "rank": 2, "status": "mp"}, {"name": "Graf/Bruckner/ Unger", "club": "Wimmer Gym Oberschützen", "timeText": "Fehlst", "status": "mp", "yearOfBirth": 2012}, {"name": "Bauer/Feichtinger/", "club": "SMS Güssing", "timeText": "Fehlst", "rank": 8, "status": "mp"}, {"name": "Schnabel/Bonyhadi", "club": "SMS Oberschützen", "timeText": "Fehlst", "status": "mp"}, {"name": "Brünner/Gabriel/", "club": "BG/BRG Oberschützen", "timeText": "Fehlst", "status": "mp"}], "courseLengthM": 1400, "courseClimbM": 65, "courseControls": 9}, {"name": "Schnupper (Oberstufe)", "declaredStarters": 26, "results": [{"name": "Sonnberger/Sommer", "club": "Jennersdorf", "timeText": "28:32", "rank": 1, "timeS": 1712, "status": "ok"}, {"name": "Tropper/Geringer", "club": "BORG Jennersdorf", "timeText": "29:37", "rank": 2, "timeS": 1777, "status": "ok"}, {"name": "Tomsits /Klinger", "club": "BAfEP Oberwart", "timeText": "30:34", "rank": 3, "timeS": 1834, "status": "ok"}, {"name": "Rogatsch/Kaiser", "club": "Jennersdorf", "timeText": "31:51", "rank": 4, "timeS": 1911, "status": "ok"}, {"name": "Gieferl/Fartek/ Holler", "club": "BORG Jennersdorf", "timeText": "31:58", "rank": 5, "timeS": 1918, "status": "ok", "yearOfBirth": 2009}, {"name": "Zotter/Lipp Clemens/Sebastia", "club": "BORG Jennersdorf", "timeText": "35:40", "rank": 6, "timeS": 2140, "status": "ok", "yearOfBirth": 2010}, {"name": "Schmidl/Rindler", "club": "BORG Jennersdorf", "timeText": "36:30", "rank": 7, "timeS": 2190, "status": "ok"}, {"name": "Zottel/Molnar Zoey/Leonie", "club": "BAfEP Oberwart", "timeText": "39:18", "rank": 8, "timeS": 2358, "status": "ok", "yearOfBirth": 2010}, {"name": "Schwab/Waltersdorfer", "club": "BORG Jennersdorf", "timeText": "39:32", "rank": 9, "timeS": 2372, "status": "ok"}, {"name": "Strenzl/ Prem", "club": "BORG Jennersdorf", "timeText": "41:29", "rank": 10, "timeS": 2489, "status": "ok", "yearOfBirth": 2008}, {"name": "Hofer/Ulreich/ Karner", "club": "Business Campus", "timeText": "42:03", "rank": 11, "timeS": 2523, "status": "ok", "yearOfBirth": 2009}, {"name": "Ackerl/Jalits Sebastian/Michae08", "club": "HTL Pinkafeld", "timeText": "44:36", "rank": 12, "timeS": 2676, "status": "ok"}, {"name": "Grill/Petanovits", "club": "BORG Jennersdorf", "timeText": "51:38", "rank": 13, "timeS": 3098, "status": "ok"}, {"name": "Pranger/Reitbauer/", "club": "Business Campus", "timeText": "53:19", "rank": 14, "timeS": 3199, "status": "ok"}, {"name": "Höfler/Grill Leona/Finja", "club": "BORG Jennersdorf", "timeText": "53:55", "rank": 15, "timeS": 3235, "status": "ok", "yearOfBirth": 2010}, {"name": "Abdulrazzak/Schröck", "club": "Jennersdorf", "timeText": "1:01:29", "rank": 16, "timeS": 3689, "status": "ok"}, {"name": "Kurtaj/Wedl/ Riegler", "club": "Business Campus", "timeText": "1:08:01", "rank": 17, "timeS": 4081, "status": "ok", "yearOfBirth": 2010}, {"name": "Pusztai/Marsi Erik/Leo", "club": "BAfEP Oberwart", "timeText": "Fehlst", "status": "mp", "yearOfBirth": 2007}, {"name": "Krammer/Salcak-Hlavka", "club": "Campus", "timeText": "Fehlst", "status": "mp"}, {"name": "Steiner/Ringdorfer", "club": "Business Campus", "timeText": "Fehlst", "status": "mp"}, {"name": "Koller /Gauster", "club": "Business Campus", "timeText": "Fehlst", "status": "mp"}, {"name": "Degendorfer/Mathä", "club": "BAfEP Oberwart", "timeText": "Fehlst", "status": "mp"}, {"name": "Stampfel/Müllner/", "club": "Business Campus", "timeText": "Fehlst", "status": "mp"}, {"name": "Jalits Michael", "club": "HTL Pinkafeld", "timeText": "N Ang", "status": "dns", "yearOfBirth": 2009}, {"name": "Schmidt /Petanovits", "club": "Jennersdorf", "timeText": "N Ang", "status": "dns"}, {"name": "Ulreich/Karner Antonia/Jara", "club": "Business Campus", "timeText": "N Ang", "status": "dns", "yearOfBirth": 2010}], "courseLengthM": 1900, "courseClimbM": 65, "courseControls": 12}, {"name": "Unterstufe weiblich( St)", "declaredStarters": 8, "results": [{"name": "Kerschbaum Felizia", "club": "BG/BRG Fürstenfeld", "timeText": "17:26", "rank": 1, "timeS": 1046, "status": "ok", "yearOfBirth": 2011}, {"name": "Stockinger Hanna", "club": "BG/BRG Leibnitz", "timeText": "29:45", "rank": 2, "timeS": 1785, "status": "ok", "yearOfBirth": 2010}, {"name": "Kerschbaum Gloria", "club": "BG/BRG Fürstenfeld", "timeText": "33:26", "rank": 3, "timeS": 2006, "status": "ok", "yearOfBirth": 2013}, {"name": "Koglmann Denise", "club": "BG/BRG Fürstenfeld", "timeText": "N Ang", "status": "dns", "yearOfBirth": 2011}, {"name": "Houdek Pia", "club": "BG/BRG Fürstenfeld", "timeText": "N Ang", "status": "dns", "yearOfBirth": 2011}, {"name": "Gigler Viktoria", "club": "BG/BRG Fürstenfeld", "timeText": "N Ang", "status": "dns", "yearOfBirth": 2010}, {"name": "Hackl Sophie", "club": "BG/BRG Fürstenfeld", "timeText": "N Ang", "status": "dns", "yearOfBirth": 2012}, {"name": "Herzer Paula", "club": "BG/BRG Fürstenfeld", "timeText": "N Ang", "status": "dns", "yearOfBirth": 2012}], "courseLengthM": 1800, "courseClimbM": 45, "courseControls": 12}, {"name": "Unterstufe männlich( St)", "declaredStarters": 8, "results": [{"name": "Veitsberger Mateo", "club": "BG/BRG Fürstenfeld", "timeText": "21:49", "rank": 1, "timeS": 1309, "status": "ok", "yearOfBirth": 2012}, {"name": "Senkl David", "club": "BG/BRG Fürstenfeld", "timeText": "22:23", "rank": 2, "timeS": 1343, "status": "ok", "yearOfBirth": 2012}, {"name": "Hudax Jonah", "club": "BG/BRG Fürstenfeld", "timeText": "23:43", "rank": 3, "timeS": 1423, "status": "ok", "yearOfBirth": 2013}, {"name": "Muhr Clemens", "club": "BG/BRG Fürstenfeld", "timeText": "30:41", "rank": 4, "timeS": 1841, "status": "ok", "yearOfBirth": 2012}, {"name": "Weber Jakob", "club": "BG/BRG Fürstenfeld", "timeText": "30:42", "rank": 5, "timeS": 1842, "status": "ok", "yearOfBirth": 2012}, {"name": "Schnepf Timo", "club": "BG/BRG Fürstenfeld", "timeText": "34:40", "rank": 6, "timeS": 2080, "status": "ok", "yearOfBirth": 2012}, {"name": "Riegler Alexander", "club": "BG/BRG Fürstenfeld", "timeText": "1:05:26", "rank": 7, "timeS": 3926, "status": "ok", "yearOfBirth": 2013}, {"name": "Feutl Paul", "club": "BG/BRG Fürstenfeld", "timeText": "N Ang", "status": "dns", "yearOfBirth": 2012}], "courseLengthM": 2000, "courseClimbM": 80, "courseControls": 12}, {"name": "Oberstufe weiblich ( St)", "declaredStarters": 3, "results": [{"name": "Dormann Hannah", "club": "BG/BRG Leibnitz", "timeText": "34:01", "rank": 1, "timeS": 2041, "status": "ok", "yearOfBirth": 2010}, {"name": "Asseg Sophia", "club": "BG/BRG Leibnitz", "timeText": "35:54", "rank": 2, "timeS": 2154, "status": "ok", "yearOfBirth": 2010}, {"name": "Eibel-Lenane Tara", "club": "BG/BRG Fürstenfeld", "timeText": "N Ang", "status": "dns", "yearOfBirth": 2009}], "courseLengthM": 2900, "courseClimbM": 105, "courseControls": 13}, {"name": "Rahmen1 (Unterstufe)", "declaredStarters": 15, "results": [{"name": "Vorderleitner/Kohl", "club": "G/BRG Fürstenfeld", "timeText": "21:48", "rank": 1, "timeS": 1308, "status": "ok"}, {"name": "Gütler/Orban Marcel", "club": "MS Fürstenfeld", "timeText": "27:01", "rank": 2, "timeS": 1621, "status": "ok"}, {"name": "Hirschfeld/Prinner", "club": "BG/BRG Fürstenfeld", "timeText": "28:35", "rank": 3, "timeS": 1715, "status": "ok"}, {"name": "Popov/Vilimek Anastasia/Mia", "club": "BG/BRG Fürstenfeld", "timeText": "30:18", "rank": 4, "timeS": 1818, "status": "ok", "yearOfBirth": 2012}, {"name": "Pfeifer/Lernpaß", "club": "BG/BRG Fürstenfeld", "timeText": "32:28", "rank": 5, "timeS": 1948, "status": "ok"}, {"name": "Pauss/Steiner Vinzent/Johanne1s4", "club": "BG/BRG Fürstenfeld", "timeText": "36:34", "rank": 6, "timeS": 2194, "status": "ok"}, {"name": "Bani Torfi/Bugurcu/", "club": "MS Fürstenfeld", "timeText": "40:08", "rank": 7, "timeS": 2408, "status": "ok"}, {"name": "Fritz/Wagner Laureen/Viktoria", "club": "MS Fürstenfeld", "timeText": "46:16", "rank": 8, "timeS": 2776, "status": "ok", "yearOfBirth": 2011}, {"name": "Sorger/Schweinzer/", "club": "MS Fürstenfeld", "timeText": "50:17", "rank": 9, "timeS": 3017, "status": "ok"}, {"name": "Müller/Paulitsch", "club": "BG/BRG Fürstenfeld", "timeText": "50:24", "rank": 10, "timeS": 3024, "status": "ok"}, {"name": "Kliensbiegl/Brunner/", "club": "MS Fürstenfeld", "timeText": "54:05", "rank": 11, "timeS": 3245, "status": "ok"}, {"name": "Gleichweit/Muhr", "club": "BG/BRG Fürstenfeld", "timeText": "56:12", "rank": 12, "timeS": 3372, "status": "ok"}, {"name": "Kohl/Unger Eva/Katharina", "club": "BG/BRG Fürstenfeld", "timeText": "57:57", "rank": 13, "timeS": 3477, "status": "ok", "yearOfBirth": 2013}, {"name": "Fischl/Grassler", "club": "BG/BRG Fürstenfeld", "timeText": "Fehlst", "status": "mp"}, {"name": "Lernpass Elias", "club": "BG/BRG Fürstenfeld", "timeText": "N Ang", "status": "dns", "yearOfBirth": 2013}], "courseLengthM": 1400, "courseClimbM": 65, "courseControls": 9}]}